Modeling_Transmission_Gates/rtl/mux_2x1.v
///////////////////////////////////////////////////////////////////////////////////
///               Modeling a 2x1 Mux using Transmission Gates                   ///
///                                                                             ///
///////////////////////////////////////////////////////////////////////////////////
///   XOR Module:                                                               ///
///                                                                             ///
///   Copyright 2025 Ujval Madhu, All rights reserved                           ///
///////////////////////////////////////////////////////////////////////////////////
//  CVS Log
//
//  Id: mux_2x1.v, v 1.0
//
//  $Date: 2024-07-03
//  $Revision: 1.0 $
//  $Author:  Ujval Madhu

module mux_2x1(
    input in_1,
    input in_2,
    input sel,
    output out
);
    wire sel_n;

    not n1(sel_n,sel);               // Not for obtaining the compliment of sel 

    cmos TG_1(out, in_1, sel_n, sel);    // Transmission Gate 1
    cmos TG_2(out, in_2, sel, sel_n);    // Transmission Gate 2


endmodule

Logic_Design/rtl/testbench.sv
///////////////////////////////////////////////////////////////////////////////////
///       Switch Level Modeling of a CMOS Gates and Boolean Logic               ///
///                                                                             ///
///////////////////////////////////////////////////////////////////////////////////
///   Testbench Module                                                          ///
///                                                                             ///
///   Copyright 2025 Ujval Madhu, All rights reserved                           ///
///////////////////////////////////////////////////////////////////////////////////
//  CVS Log
//
//  Id: testbench.sv, v 1.0
//
//  $Date: 2024-07-03
//  $Revision: 1.0 $
//  $Author:  Ujval Madhu

module testbench;
    reg in_a, in_b;
    reg sel;
    wire out;
    integer seed;

    // Instantiating 2x1 Transmission Gate MUX
    mux_2x1 m1(.in_1(in_a), .in_2(in_b), .sel(sel), .out(out));

    // Random Stimulus Generation
    initial begin
        seed = $random;
        $random(seed);              // Icarus doesn't support $srandom yet

        in_b = 1'b0;
        in_a = 1'b0;
        #10;
        
        for(int i = 1; i <= 10; i++) begin
            in_a = $random % 2;
            in_b = $random % 2;
            sel  = $random % 2;

            #10;
            
            $display("2x1 MUX Output: Input A: %b, Input B: %b, Sel: %b, Out: %b", in_a, in_b, sel, out);
            
            //#10
            // Verification
            // // Inverter
            // if (sel == ) begin
            //     $display("Error Detected on inverter at %t, output = %b input = %b",$time, out_inv, in); 
            //     $fatal;
            // end

            // // NAND
            // if (out_nand != ~(in_a & in_b) ) begin
            //     $display("Error Detected on NAND at %t, Output = %b , Input A= %b, Input B = %b",$time, out_nand, in_a, in_b); 
            //     $fatal;
            // end
        end
    end

    // Generating Waveform Files
    initial begin
        $dumpfile("testbench.vcd");
        $dumpvars(0, testbench);
    end

endmodule

Logic_Design/waves/testbench.vcd
$date
	Sun Mar  9 20:02:27 2025
$end
$version
	Icarus Verilog
$end
$timescale
	1ps
$end
$scope module testbench $end
$var wire 1 ! out $end
$var reg 1 " in_a $end
$var reg 1 # in_b $end
$var reg 1 $ sel $end
$var integer 32 % seed [31:0] $end
$scope module m1 $end
$var wire 1 " in_1 $end
$var wire 1 # in_2 $end
$var wire 1 ! out $end
$var wire 1 $ sel $end
$var wire 1 & sel_n $end
$upscope $end
$scope begin $ivl_for_loop0 $end
$var integer 32 ' i [31:0] $end
$upscope $end
$upscope $end
$enddefinitions $end
$comment Show the parameter values. $end
$dumpall
$end
#0
$dumpvars
b0 '
x&
b11000011110100100110000111010101 %
x$
0#
0"
x!
$end
#10000
0&
1$
1#
1!
1"
b1 '
#20000
b10 '
#30000
0"
b11 '
#40000
b100 '
#50000
1&
0!
0$
b101 '
#60000
0&
1$
0#
0!
1"
b110 '
#70000
b111 '
#80000
1&
0$
0"
b1000 '
#90000
0&
1$
0!
1"
b1001 '
#100000
1!
1#
b1010 '
#110000
b1011 '
