Logic_Design/rtl/ThreeOFive.v
///////////////////////////////////////////////////////////////////////////////////
///                       Three Out of Five Output                              ///
///                                                                             ///
///////////////////////////////////////////////////////////////////////////////////
///   threeOfive: A circuit that generates a high only when any three of its    ///
///   five inputs are active, more than 3 is a low.                             ///
///                                                                             ///
///   Copyright 2025 Ujval Madhu, All rights reserved                           ///
///////////////////////////////////////////////////////////////////////////////////
//  CVS Log
//
//  Id: mux_2x1.v, v 1.0
//
//  $Date: 2024-07-03
//  $Revision: 1.0 $
//  $Author:  Ujval Madhu

module threeOfive(
    input in_1,
    input in_2,
    input in_3,
    input in_4,
    input in_5,

    output out
);

    assign out = (in_1 + in_2 + in_3 + in_4 + in_5 == 2'b11);


endmodule

Logic_Design/rtl/testbench.sv
///////////////////////////////////////////////////////////////////////////////////
///                      Logic Designs Testbench                                ///
///                                                                             ///
///////////////////////////////////////////////////////////////////////////////////
///   Testbench Module                                                          ///
///                                                                             ///
///   Copyright 2025 Ujval Madhu, All rights reserved                           ///
///////////////////////////////////////////////////////////////////////////////////
//  CVS Log
//
//  Id: testbench.sv, v 1.0
//
//  $Date: 2024-07-03
//  $Revision: 1.0 $
//  $Author:  Ujval Madhu

module testbench;
    reg in_1, in_2, in_3, in_4, in_5;
    wire out;
    integer seed;

    // Instantiating 2x1 Transmission Gate MUX
    threeOfive m1(.in_1(in_1), .in_2(in_2), .in_3(in_3), .in_4(in_4), .in_5(in_5), .out(out));

    // Random Stimulus Generation
    initial begin
        seed = $random;
        $random(seed);              // Icarus doesn't support $srandom yet

        in_1 = 1'b0;
        in_2 = 1'b0;
        in_3 = 1'b0;
        in_4 = 1'b0;
        in_5 = 1'b0;

        #10;
        
        for(int i = 1; i <= 10; i++) begin
            in_1 = $random % 2;
            in_2 = $random % 2;
            in_3 = $random % 2;
            in_4 = $random % 2;
            in_5 = $random % 2;

            #10;
            
            $display("ThreeOFive Output: Input 1: %b, Input 2: %b, Input 3: %b, Input 4: %b, Input 5: %b, Out: %b", in_1, in_2, in_3, in_4, in_5, out);
            
            //#10
            // Verification
            // // Inverter
            // if (sel == ) begin
            //     $display("Error Detected on inverter at %t, output = %b input = %b",$time, out_inv, in); 
            //     $fatal;
            // end

            // // NAND
            // if (out_nand != ~(in_a & in_b) ) begin
            //     $display("Error Detected on NAND at %t, Output = %b , Input A= %b, Input B = %b",$time, out_nand, in_a, in_b); 
            //     $fatal;
            // end
        end
    end

    // Generating Waveform Files
    initial begin
        $dumpfile("testbench.vcd");
        $dumpvars(0, testbench);
    end

endmodule

Logic_Design/waves/testbench.vcd
$date
	Wed Mar 26 14:52:46 2025
$end
$version
	Icarus Verilog
$end
$timescale
	1ps
$end
$scope module testbench $end
$var wire 1 ! out $end
$var reg 1 " in_1 $end
$var reg 1 # in_2 $end
$var reg 1 $ in_3 $end
$var reg 1 % in_4 $end
$var reg 1 & in_5 $end
$var integer 32 ' seed [31:0] $end
$scope module m1 $end
$var wire 1 " in_1 $end
$var wire 1 # in_2 $end
$var wire 1 $ in_3 $end
$var wire 1 % in_4 $end
$var wire 1 & in_5 $end
$var wire 1 ! out $end
$upscope $end
$scope begin $ivl_for_loop0 $end
$var integer 32 ( i [31:0] $end
$upscope $end
$upscope $end
$enddefinitions $end
$comment Show the parameter values. $end
$dumpall
$end
#0
$dumpvars
b0 (
b11000011110100100110000111010101 '
0&
0%
0$
0#
0"
0!
$end
#10000
1&
1%
0!
1$
1#
1"
b1 (
#20000
1!
0&
0#
b10 (
#30000
0$
1!
1#
b11 (
#40000
1$
1!
0#
b100 (
#50000
1&
0%
0!
0$
b101 (
#60000
1%
0!
1$
1#
0"
b110 (
#70000
0%
0$
0!
0#
b111 (
#80000
1%
0!
1$
1#
b1000 (
#90000
1!
0$
0#
1"
b1001 (
#100000
0&
0!
0%
b1010 (
#110000
b1011 (
