Carry_Look_Ahead_Adder/rtl/cla.v
///////////////////////////////////////////////////////////////////////////////////
///                      4-Bit Carry Look Ahead Adder                           ///
///                                                                             ///
///////////////////////////////////////////////////////////////////////////////////
///   CLA Module:  4-Bit Implementation of the Carry Lookahead Adder (CLA)      ///
///                                                                             ///
///   Copyright 2025 Ujval Madhu, All rights reserved                           ///
///////////////////////////////////////////////////////////////////////////////////
//  CVS Log
//
//  Id: cla.v, v 1.0
//
//  $Date: 2024-07-03
//  $Revision: 1.0 $
//  $Author:  Ujval Madhu

module cla_4b(
    input [3:0] a,
    input [3:0] b,
    input c0,      // Carry In
    output [3:0] sum,
    output c_out
);

wire [3:0] p, g;   // Propagate and Generate Bits for each bit position
wire [4:1] c;      // Carry out for each bit 

assign  p[0] = a[0] ^ b[0],
        p[1] = a[1] ^ b[1],
        p[2] = a[2] ^ b[2],
        p[3] = a[3] ^ b[3];

assign  g[0] = a[0] & b[0],
        g[1] = a[1] & b[1],
        g[2] = a[2] & b[2],
        g[3] = a[3] & b[3];

assign  c[1] = g[0] | p[0] & c[0],
        c[2] = g[1] | (p[1] & (g[0] | p[0] & c[0])),
        c[3] = g[2] | (p[2] & (g[1] | (p[1] & (g[0] | p[0] & c[0])))),
        c[4] = g[3] | (p[3] & (g[2] | (p[2] & (g[1] | (p[1] & (g[0] | p[0] & c[0]))))));

assign  sum[0] = p[0] ^ a[0],
        sum[1] = p[1] ^ a[1],
        sum[2] = p[2] ^ a[2],
        sum[3] = p[3] ^ a[3];

assign c_out = c[4];        

endmodule

Carry_Look_Ahead_Adder/rtl/testbench.sv
///////////////////////////////////////////////////////////////////////////////////
///       Switch Level Modeling of a CMOS Gates and Boolean Logic               ///
///                                                                             ///
///////////////////////////////////////////////////////////////////////////////////
///   Testbench Module                                                          ///
///                                                                             ///
///   Copyright 2025 Ujval Madhu, All rights reserved                           ///
///////////////////////////////////////////////////////////////////////////////////
//  CVS Log
//
//  Id: testbench.sv, v 1.0
//
//  $Date: 2024-07-03
//  $Revision: 1.0 $
//  $Author:  Ujval Madhu

module testbench;

    parameter num_bits = 4;

    reg [num_bits -1:0] in_a;
    reg [num_bits -1:0] in_b;
    reg c0;
    reg [num_bits -1:0]sum;
    reg c_out;
    integer seed;

    // Instantiating the CLA module
    cla_4b cla_adder(.a(in_a), .b(in_b), .c0(c0), .sum(sum), .c_out(c_out));

    // Random Stimulus Generation
    initial begin
        seed = $random;
        $random(seed);              // Icarus doesn't support $srandom yet

        in_b = 4'b0;
        in_a = 4'b0;
        #10;
        
        for(int i = 1; i <= 10; i++) begin
            in_a = $random % (2**num_bits);
            in_b = $random % (2**num_bits);
            c0   = $random % (2);

            #10;
            
            $display("CLA Result: Input A: %4b, Input B: %4b, C0: %0b, Sum: %4b, C_out: %0b", in_a, in_b, c0, sum, c_out);
            
            //#10
            // Verification
            // // Inverter
            // if (sel == ) begin
            //     $display("Error Detected on inverter at %t, output = %b input = %b",$time, out_inv, in); 
            //     $fatal;
            // end

            // // NAND
            // if (out_nand != ~(in_a & in_b) ) begin
            //     $display("Error Detected on NAND at %t, Output = %b , Input A= %b, Input B = %b",$time, out_nand, in_a, in_b); 
            //     $fatal;
            // end
        end
    end

    // Generating Waveform Files
    initial begin
        $dumpfile("testbench.vcd");
        $dumpvars(0, testbench);
    end

endmodule

Carry_Look_Ahead_Adder/waves/testbench.vcd
$date
	Tue Mar 11 20:27:28 2025
$end
$version
	Icarus Verilog
$end
$timescale
	1ps
$end
$scope module testbench $end
$var wire 4 ! sum [3:0] $end
$var wire 1 " c_out $end
$var parameter 32 # num_bits $end
$var reg 1 $ c0 $end
$var reg 4 % in_a [3:0] $end
$var reg 4 & in_b [3:0] $end
$var integer 32 ' seed [31:0] $end
$scope module cla_adder $end
$var wire 4 ( a [3:0] $end
$var wire 4 ) b [3:0] $end
$var wire 1 $ c0 $end
$var wire 4 * sum [3:0] $end
$var wire 4 + p [3:0] $end
$var wire 4 , g [3:0] $end
$var wire 1 " c_out $end
$var wire 4 - c [4:1] $end
$upscope $end
$scope begin $ivl_for_loop0 $end
$var integer 32 . i [31:0] $end
$upscope $end
$upscope $end
$enddefinitions $end
$comment Show the parameter values. $end
$dumpall
b100 #
$end
#0
$dumpvars
b0 .
b0 -
b0 ,
b0 +
b0 *
b0 )
b0 (
b11000011110100100110000111010101 '
b0 &
b0 %
x$
0"
b0 !
$end
#10000
b1 -
b1000 +
b1 ,
b1001 !
b1001 *
1$
b1001 &
b1001 )
b1 %
b1 (
b1 .
#20000
1"
b1101 -
b0 +
b1101 ,
b1101 !
b1101 *
b1101 &
b1101 )
b1101 %
b1101 (
b10 .
#30000
0"
b0xx -
b11 +
b0 ,
b1 !
b1 *
b1 &
b1 )
b10 %
b10 (
b11 .
#40000
1"
b11xx -
b1011 +
b100 ,
b1101 !
b1101 *
b1101 &
b1101 )
b110 %
b110 (
b100 .
#50000
b100x -
b101 +
b1000 ,
b1001 !
b1001 *
0$
b1001 &
b1001 )
b1100 %
b1100 (
b101 .
#60000
x"
bx -
b1111 +
b0 ,
b1010 !
b1010 *
1$
b1010 &
b1010 )
b101 %
b101 (
b110 .
#70000
0"
b11x -
b101 +
b10 ,
b10 !
b10 *
b10 &
b10 )
b111 %
b111 (
b111 .
#80000
1"
b1110 -
b1100 +
b1110 !
b1110 *
0$
b1110 &
b1110 )
b10 %
b10 (
b1000 .
#90000
b110x -
b1001 +
b100 ,
b1100 !
b1100 *
1$
b1100 &
b1100 )
b101 %
b101 (
b1001 .
#100000
b1101 -
b1000 +
b101 ,
b101 !
b101 *
b101 &
b101 )
b1101 %
b1101 (
b1010 .
#110000
b1011 .
