Counters/rtl/dff.v
///////////////////////////////////////////////////////////////////////////////////
///                         A Standard D Flip Flop                              ///
///                                                                             ///
///////////////////////////////////////////////////////////////////////////////////
///   This is a Standard DFF implementation                                     ///
///                                                                             ///
///   Copyright 2025 Ujval Madhu, All rights reserved                           ///
///////////////////////////////////////////////////////////////////////////////////
//  CVS Log
//
//  Id: dff.v, v 1.0
//
//  $Date: 2024-01-04
//  $Revision: 1.0 $
//  $Author:  Ujval Madhu

module dff(
    input clk,
    input rst_n,
    input d,
    output reg q
);

always @(posedge clk or negedge rst_n) begin
    if (!rst_n) q <= 0;
    else q <= d;
end

endmodule

Counters/rtl/xor.v
///////////////////////////////////////////////////////////////////////////////////
///             Switch Level Modeling of a CMOS XOR Gate                       ///
///                                                                             ///
///////////////////////////////////////////////////////////////////////////////////
///   XOR Module:                                                              ///
///                                                                             ///
///   Copyright 2025 Ujval Madhu, All rights reserved                           ///
///////////////////////////////////////////////////////////////////////////////////
//  CVS Log
//
//  Id: xor.v, v 1.0
//
//  $Date: 2024-07-03
//  $Revision: 1.0 $
//  $Author:  Ujval Madhu

module cmos_xor(
    input in_a,
    input in_b,
    output out
);
    supply1 vdd;
    supply0 gnd;
    wire w1p, w2p, w3n, w4n;

    // Argument order (Drain, Source, gate)
    // PMOS A.B' + A'.B = XOR      
    pmos p1(w1p, vdd, in_a);
    pmos p2(out, w1p, ~in_b);

    pmos p3(w2p, vdd, ~in_a);
    pmos p4(out, w2p, in_b);

    // NMOS A.B + A'.B'   ; complement of the PMOS
    nmos n1(w1n, gnd, in_b);
    nmos n2(out, w1n, in_a);

    nmos n3(w2n, gnd, ~in_b);
    nmos n4(out, w2n, ~in_a);

endmodule

Counters/rtl/tff.v
///////////////////////////////////////////////////////////////////////////////////
///                            T Flip Flop Design                               ///
///                                                                             ///
///////////////////////////////////////////////////////////////////////////////////
///   In this design a T Flip Flop is implemented using a D FF                  ///
///                                                                             ///
///   Copyright 2025 Ujval Madhu, All rights reserved                           ///
///////////////////////////////////////////////////////////////////////////////////
//  CVS Log
//
//  Id: tff.v, v 1.0
//
//  $Date: 2024-01-04
//  $Revision: 1.0 $
//  $Author:  Ujval Madhu

module tff(
    input rst_n,
    input clk,
    input t,
    output q
);

wire d;
wire q_internal;

// Using XOR combinational logic to convert t to d
//assign d = t ^ q_internal;
cmos_xor xor1(
    .in_a(t),
    .in_b(q_internal),
    .out(d)
);

// Instantiating DFF
dff dff2(
    .rst_n(rst_n),
    .clk(clk),
    .d(d),
    .q(q_internal)
);

assign q = q_internal;

endmodule

Counters/rtl/mod16_T.v
///////////////////////////////////////////////////////////////////////////////////
///       4-Bit Ripple Counter or Mod 16 Counter using T flip Flops             ///
///                                                                             ///
///////////////////////////////////////////////////////////////////////////////////
///   This is a design for a 4 bit asynchronous Ripple counter using T FFs      ///
///                                                                             ///
///   Copyright 2025 Ujval Madhu, All rights reserved                           ///
///////////////////////////////////////////////////////////////////////////////////
//  CVS Log
//
//  Id: mod16_T.v, v 1.0
//
//  $Date: 2024-07-03
//  $Revision: 1.0 $
//  $Author:  Ujval Madhu

module mod16_T(
    input clk,
    input rst_n,
    input [3:0] t,
    output [3:0] q 
);

    // create 4 instances of TFF connected in cascade
    tff tff0(.clk(clk), .rst_n(rst_n), .t(1'b1), .q(q[0]));
    genvar i;
    generate
        for (i = 1; i<4; i++) begin
            tff tffx(.clk(q[i-1]), .rst_n(rst_n), .t(1'b1), .q(q[i]));
        end
    endgenerate

endmodule

Counters/rtl/jkff.v
///////////////////////////////////////////////////////////////////////////////////
///                        A Standard JK Flip Flop                              ///
///                                                                             ///
///////////////////////////////////////////////////////////////////////////////////
///   This is a Standard DFF implementation                                     ///
///                                                                             ///
///   Copyright 2025 Ujval Madhu, All rights reserved                           ///
///////////////////////////////////////////////////////////////////////////////////
//  CVS Log
//
//  Id: jkff.v, v 1.0
//
//  $Date: 2024-01-04
//  $Revision: 1.0 $
//  $Author:  Ujval Madhu

module jkff(
    input clk,
    input rst_n,
    input j,k,
    output reg q
);

always @(posedge clk) begin
    if (!rst_n) q <= 0;
    else begin
        case({j,k})
            2'b00: q <= q;
            2'b01: q <= 1'b0;
            2'b10: q <= 1'b1;
            2'b11: q <= ~q;
        endcase
    end
end

endmodule

Counters/rtl/testbench.sv
///////////////////////////////////////////////////////////////////////////////////
///       Switch Level Modeling of a CMOS Gates and Boolean Logic               ///
///                                                                             ///
///////////////////////////////////////////////////////////////////////////////////
///   Testbench Module                                                          ///
///                                                                             ///
///   Copyright 2025 Ujval Madhu, All rights reserved                           ///
///////////////////////////////////////////////////////////////////////////////////
//  CVS Log
//
//  Id: testbench.sv, v 1.0
//
//  $Date: 2024-07-03
//  $Revision: 1.0 $
//  $Author:  Ujval Madhu

module testbench;
    reg in, in_b;
    reg rst_n, clk;
    wire out_dff;
    wire out_tff;
    wire out_jkff;
    wire [3:0] q16_t;
    integer seed;

    //Clock Generation
    initial begin
        clk = 1'b0;
        repeat(500) #5 clk = ~clk;
    end

    // Reset Generation
    initial begin
        rst_n = 1'b1;
        repeat(10) @(posedge clk)
        rst_n = 1'b0;
        repeat(10) @(posedge clk)
        rst_n = 1'b1;
    end

    // Instantiating DFF
    dff dff1(.clk(clk), .rst_n(rst_n), .d(in), .q(out_dff));

    // Instantiating TFF 
    tff tff1(.clk(clk),.rst_n(rst_n), .t(in), .q(out_tff));

    // Instantiating JK FF 
    jkff jkff1(.clk(clk),.rst_n(rst_n), .j(in), .k(in_b), .q(out_jkff));

    // Instantiating Mod16 Ripple Counter built with T flip Flops
    mod16_T m16T(.clk(clk), .rst_n(rst_n), .t(4'b1111), .q(q16_t));

    // Random Stimulus Generation
    initial begin
        seed = $random;
        $random(seed);              // Icarus doesn't support $srandom yet

        in = 1'b0;
        in_b = 1'b0;
        #10;
        
        for(int i = 1; i <= 100; i++) begin
            in = $random % 2;
            in_b = $random % 2;

            @(posedge clk)
            #1
            $display("DFF Input: %b Output:%b", in, out_dff);
            $display("TFF Input: %b Output:%b", in, out_tff);
            $display("JKFF Input J: %b Input K: %b Output:%b\n", in, in_b, out_jkff);


        end
    end

    // Generating Waveform Files
    initial begin
        $dumpfile("testbench.vcd");
        $dumpvars(0, testbench);
    end

endmodule

Counters/waves/testbench.vcd
$date
	Wed Apr  2 08:46:46 2025
$end
$version
	Icarus Verilog
$end
$timescale
	1ps
$end
$scope module testbench $end
$var wire 4 ! q16_t [3:0] $end
$var wire 1 " out_tff $end
$var wire 1 # out_jkff $end
$var wire 1 $ out_dff $end
$var reg 1 % clk $end
$var reg 1 & in $end
$var reg 1 ' in_b $end
$var reg 1 ( rst_n $end
$var integer 32 ) seed [31:0] $end
$scope module dff1 $end
$var wire 1 % clk $end
$var wire 1 & d $end
$var wire 1 ( rst_n $end
$var reg 1 $ q $end
$upscope $end
$scope module jkff1 $end
$var wire 1 % clk $end
$var wire 1 & j $end
$var wire 1 ' k $end
$var wire 1 ( rst_n $end
$var reg 1 # q $end
$upscope $end
$scope module m16T $end
$var wire 1 % clk $end
$var wire 1 ( rst_n $end
$var wire 4 * t [3:0] $end
$var wire 4 + q [3:0] $end
$scope begin genblk1[1] $end
$var parameter 2 , i $end
$scope module tffx $end
$var wire 1 - clk $end
$var wire 1 . d $end
$var wire 1 / q $end
$var wire 1 ( rst_n $end
$var wire 1 0 t $end
$var wire 1 1 q_internal $end
$scope module dff2 $end
$var wire 1 - clk $end
$var wire 1 . d $end
$var wire 1 ( rst_n $end
$var reg 1 1 q $end
$upscope $end
$scope module xor1 $end
$var wire 1 2 gnd $end
$var wire 1 0 in_a $end
$var wire 1 1 in_b $end
$var wire 1 . out $end
$var wire 1 3 vdd $end
$var wire 1 4 w1n $end
$var wire 1 5 w1p $end
$var wire 1 6 w2n $end
$var wire 1 7 w2p $end
$upscope $end
$upscope $end
$upscope $end
$scope begin genblk1[2] $end
$var parameter 3 8 i $end
$scope module tffx $end
$var wire 1 9 clk $end
$var wire 1 : d $end
$var wire 1 ; q $end
$var wire 1 ( rst_n $end
$var wire 1 < t $end
$var wire 1 = q_internal $end
$scope module dff2 $end
$var wire 1 9 clk $end
$var wire 1 : d $end
$var wire 1 ( rst_n $end
$var reg 1 = q $end
$upscope $end
$scope module xor1 $end
$var wire 1 > gnd $end
$var wire 1 < in_a $end
$var wire 1 = in_b $end
$var wire 1 : out $end
$var wire 1 ? vdd $end
$var wire 1 @ w1n $end
$var wire 1 A w1p $end
$var wire 1 B w2n $end
$var wire 1 C w2p $end
$upscope $end
$upscope $end
$upscope $end
$scope begin genblk1[3] $end
$var parameter 3 D i $end
$scope module tffx $end
$var wire 1 E clk $end
$var wire 1 F d $end
$var wire 1 G q $end
$var wire 1 ( rst_n $end
$var wire 1 H t $end
$var wire 1 I q_internal $end
$scope module dff2 $end
$var wire 1 E clk $end
$var wire 1 F d $end
$var wire 1 ( rst_n $end
$var reg 1 I q $end
$upscope $end
$scope module xor1 $end
$var wire 1 J gnd $end
$var wire 1 H in_a $end
$var wire 1 I in_b $end
$var wire 1 F out $end
$var wire 1 K vdd $end
$var wire 1 L w1n $end
$var wire 1 M w1p $end
$var wire 1 N w2n $end
$var wire 1 O w2p $end
$upscope $end
$upscope $end
$upscope $end
$scope module tff0 $end
$var wire 1 % clk $end
$var wire 1 P d $end
$var wire 1 Q q $end
$var wire 1 ( rst_n $end
$var wire 1 R t $end
$var wire 1 S q_internal $end
$scope module dff2 $end
$var wire 1 % clk $end
$var wire 1 P d $end
$var wire 1 ( rst_n $end
$var reg 1 S q $end
$upscope $end
$scope module xor1 $end
$var wire 1 T gnd $end
$var wire 1 R in_a $end
$var wire 1 S in_b $end
$var wire 1 P out $end
$var wire 1 U vdd $end
$var wire 1 V w1n $end
$var wire 1 W w1p $end
$var wire 1 X w2n $end
$var wire 1 Y w2p $end
$upscope $end
$upscope $end
$upscope $end
$scope module tff1 $end
$var wire 1 % clk $end
$var wire 1 Z d $end
$var wire 1 " q $end
$var wire 1 ( rst_n $end
$var wire 1 & t $end
$var wire 1 [ q_internal $end
$scope module dff2 $end
$var wire 1 % clk $end
$var wire 1 Z d $end
$var wire 1 ( rst_n $end
$var reg 1 [ q $end
$upscope $end
$scope module xor1 $end
$var wire 1 \ gnd $end
$var wire 1 & in_a $end
$var wire 1 [ in_b $end
$var wire 1 Z out $end
$var wire 1 ] vdd $end
$var wire 1 ^ w1n $end
$var wire 1 _ w1p $end
$var wire 1 ` w2n $end
$var wire 1 a w2p $end
$upscope $end
$upscope $end
$scope begin $ivl_for_loop0 $end
$var integer 32 b i [31:0] $end
$upscope $end
$upscope $end
$enddefinitions $end
$comment Show the parameter values. $end
$dumpall
b11 D
b10 8
b1 ,
$end
#0
$dumpvars
b0 b
za
x`
1_
x^
1]
0\
x[
xZ
1Y
xX
zW
xV
1U
0T
xS
1R
xQ
xP
1O
xN
zM
xL
1K
0J
xI
1H
xG
xF
xE
1C
xB
zA
x@
1?
0>
x=
1<
x;
x:
x9
17
x6
z5
x4
13
02
x1
10
x/
x.
x-
bx +
b1111 *
b11000011110100100110000111010101 )
1(
0'
0&
0%
x$
x#
x"
bx !
$end
#5000
06
09
0B
0E
0N
0Z
0`
0X
0-
1.
z4
0/
01
1:
z@
0;
0=
1F
zL
0G
0I
0$
z^
0"
0[
1P
zV
b0 !
b0 +
0Q
0S
0#
0(
1%
#10000
1a
1Z
0%
1'
z_
1&
b1 b
#15000
1%
#16000
b10 b
#20000
0%
#25000
1%
#26000
b11 b
#30000
0%
#35000
1%
#36000
za
0Z
1_
0&
b100 b
#40000
0%
#45000
1%
#46000
1a
1Z
0'
z_
1&
b101 b
#50000
0%
#55000
1%
#56000
1'
b110 b
#60000
0%
#65000
1%
#66000
za
0Z
1_
0&
b111 b
#70000
0%
#75000
1%
#76000
b1000 b
#80000
0%
#85000
1%
#86000
b1001 b
#90000
0%
#95000
1%
#96000
1a
1Z
0'
z_
1&
b1010 b
#100000
0%
#105000
zN
0F
0L
1G
1I
zB
1E
0:
0@
1;
1=
z6
19
0.
04
1/
11
z`
zX
1-
1$
0Z
0^
1"
1[
0P
0V
b1111 !
b1111 +
1Q
1S
1#
1(
1%
#106000
b1011 b
#110000
0%
#115000
0X
0-
0`
1P
zV
b1110 !
b1110 +
0Q
0S
1Z
z^
0"
0[
1%
#116000
za
0Z
1_
0&
b1100 b
#120000
0%
#125000
06
09
1.
z4
0/
01
zX
1-
0$
0P
0V
b1101 !
b1101 +
1Q
1S
1%
#126000
1a
1Z
z_
1&
b1101 b
#130000
0%
#135000
0X
0-
z`
1P
zV
b1100 !
b1100 +
0Q
0S
0Z
0^
1"
1[
1$
1%
#136000
1'
b1110 b
#140000
0%
#145000
0B
0E
1:
z@
0;
0=
z6
19
0.
04
1/
11
0`
zX
1-
1Z
z^
0"
0[
0P
0V
b1011 !
b1011 +
1Q
1S
0#
1%
#146000
b1111 b
#150000
0%
#155000
0X
0-
z`
1P
zV
b1010 !
b1010 +
0Q
0S
0Z
0^
1"
1[
1#
1%
#156000
za
0'
1_
1Z
0&
b10000 b
#160000
0%
#165000
06
09
1.
z4
0/
01
zX
1-
0$
0P
0V
b1001 !
b1001 +
1Q
1S
1%
#166000
b10001 b
#170000
0%
#175000
0X
0-
1P
zV
b1000 !
b1000 +
0Q
0S
1%
#176000
1a
z_
0Z
1&
b10010 b
#180000
0%
#185000
0N
1F
zL
0G
0I
zB
1E
0:
0@
1;
1=
z6
19
0.
04
1/
11
0`
zX
1-
1$
1Z
z^
0"
0[
0P
0V
b111 !
b111 +
1Q
1S
1%
#186000
1'
b10011 b
#190000
0%
#195000
0X
0-
z`
1P
zV
b110 !
b110 +
0Q
0S
0Z
0^
1"
1[
0#
1%
#196000
b10100 b
#200000
0%
#205000
06
09
1.
z4
0/
01
0`
zX
1-
1Z
z^
0"
0[
0P
0V
b101 !
b101 +
1Q
1S
1#
1%
#206000
0'
b10101 b
#210000
0%
#215000
0X
0-
z`
1P
zV
b100 !
b100 +
0Q
0S
0Z
0^
1"
1[
1%
#216000
za
1'
1_
1Z
0&
b10110 b
#220000
0%
#225000
0B
0E
1:
z@
0;
0=
z6
19
0.
04
1/
11
zX
1-
0$
0P
0V
b11 !
b11 +
1Q
1S
0#
1%
#226000
1a
z_
0Z
1&
b10111 b
#230000
0%
#235000
0X
0-
0`
1P
zV
b10 !
b10 +
0Q
0S
1Z
z^
0"
0[
1$
1#
1%
#236000
za
0Z
0'
1_
0&
b11000 b
#240000
0%
#245000
06
09
1.
z4
0/
01
zX
1-
0$
0P
0V
b1 !
b1 +
1Q
1S
1%
#246000
b11001 b
#250000
0%
#255000
0X
0-
1P
zV
b0 !
b0 +
0Q
0S
1%
#256000
1'
b11010 b
#260000
0%
#265000
zN
0F
0L
1G
1I
zB
1E
0:
0@
1;
1=
z6
19
0.
04
1/
11
zX
1-
0P
0V
b1111 !
b1111 +
1Q
1S
0#
1%
#266000
0'
b11011 b
#270000
0%
#275000
0X
0-
1P
zV
b1110 !
b1110 +
0Q
0S
1%
#276000
1a
1Z
1'
z_
1&
b11100 b
#280000
0%
#285000
06
09
1.
z4
0/
01
z`
zX
1-
1$
0Z
0^
1"
1[
0P
0V
b1101 !
b1101 +
1Q
1S
1#
1%
#286000
za
0'
1_
1Z
0&
b11101 b
#290000
0%
#295000
0X
0-
1P
zV
b1100 !
b1100 +
0Q
0S
0$
1%
#296000
b11110 b
#300000
0%
#305000
0B
0E
1:
z@
0;
0=
z6
19
0.
04
1/
11
zX
1-
0P
0V
b1011 !
b1011 +
1Q
1S
1%
#306000
1'
b11111 b
#310000
0%
#315000
0X
0-
1P
zV
b1010 !
b1010 +
0Q
0S
0#
1%
#316000
1a
z_
0Z
1&
b100000 b
#320000
0%
#325000
06
09
1.
z4
0/
01
0`
zX
1-
1$
1Z
z^
0"
0[
0P
0V
b1001 !
b1001 +
1Q
1S
1#
1%
#326000
b100001 b
#330000
0%
#335000
0X
0-
z`
1P
zV
b1000 !
b1000 +
0Q
0S
0Z
0^
1"
1[
0#
1%
#336000
za
0'
1_
1Z
0&
b100010 b
#340000
0%
#345000
0N
1F
zL
0G
0I
zB
1E
0:
0@
1;
1=
z6
19
0.
04
1/
11
zX
1-
0$
0P
0V
b111 !
b111 +
1Q
1S
1%
#346000
1a
1'
z_
0Z
1&
b100011 b
#350000
0%
#355000
0X
0-
0`
1P
zV
b110 !
b110 +
0Q
0S
1Z
z^
0"
0[
1$
1#
1%
#356000
0'
b100100 b
#360000
0%
#365000
06
09
1.
z4
0/
01
z`
zX
1-
0Z
0^
1"
1[
0P
0V
b101 !
b101 +
1Q
1S
1%
#366000
za
1'
1_
1Z
0&
b100101 b
#370000
0%
#375000
0X
0-
1P
zV
b100 !
b100 +
0Q
0S
0$
0#
1%
#376000
1a
0'
z_
0Z
1&
b100110 b
#380000
0%
#385000
0B
0E
1:
z@
0;
0=
z6
19
0.
04
1/
11
0`
zX
1-
1$
1Z
z^
0"
0[
0P
0V
b11 !
b11 +
1Q
1S
1#
1%
#386000
1'
b100111 b
#390000
0%
#395000
0X
0-
z`
1P
zV
b10 !
b10 +
0Q
0S
0Z
0^
1"
1[
0#
1%
#396000
za
1_
1Z
0&
b101000 b
#400000
0%
#405000
06
09
1.
z4
0/
01
zX
1-
0$
0P
0V
b1 !
b1 +
1Q
1S
1%
#406000
1a
z_
0Z
1&
b101001 b
#410000
0%
#415000
0X
0-
0`
1P
zV
b0 !
b0 +
0Q
0S
1Z
z^
0"
0[
1$
1#
1%
#416000
za
0Z
1_
0&
b101010 b
#420000
0%
#425000
zN
0F
0L
1G
1I
zB
1E
0:
0@
1;
1=
z6
19
0.
04
1/
11
zX
1-
0$
0P
0V
b1111 !
b1111 +
1Q
1S
0#
1%
#426000
1a
1Z
0'
z_
1&
b101011 b
#430000
0%
#435000
0X
0-
z`
1P
zV
b1110 !
b1110 +
0Q
0S
0Z
0^
1"
1[
1$
1#
1%
#436000
za
1_
1Z
0&
b101100 b
#440000
0%
#445000
06
09
1.
z4
0/
01
zX
1-
0$
0P
0V
b1101 !
b1101 +
1Q
1S
1%
#446000
1'
b101101 b
#450000
0%
#455000
0X
0-
1P
zV
b1100 !
b1100 +
0Q
0S
0#
1%
#456000
1a
0'
z_
0Z
1&
b101110 b
#460000
0%
#465000
0B
0E
1:
z@
0;
0=
z6
19
0.
04
1/
11
0`
zX
1-
1$
1Z
z^
0"
0[
0P
0V
b1011 !
b1011 +
1Q
1S
1#
1%
#466000
za
0Z
1'
1_
0&
b101111 b
#470000
0%
#475000
0X
0-
1P
zV
b1010 !
b1010 +
0Q
0S
0$
0#
1%
#476000
1a
1Z
z_
1&
b110000 b
#480000
0%
#485000
06
09
1.
z4
0/
01
z`
zX
1-
1$
0Z
0^
1"
1[
0P
0V
b1001 !
b1001 +
1Q
1S
1#
1%
#486000
b110001 b
#490000
0%
#495000
0X
0-
0`
1P
zV
b1000 !
b1000 +
0Q
0S
1Z
z^
0"
0[
0#
1%
#496000
za
0Z
1_
0&
b110010 b
#500000
0%
#505000
0N
1F
zL
0G
0I
zB
1E
0:
0@
1;
1=
z6
19
0.
04
1/
11
zX
1-
0$
0P
0V
b111 !
b111 +
1Q
1S
1%
#506000
1a
1Z
z_
1&
b110011 b
#510000
0%
#515000
0X
0-
z`
1P
zV
b110 !
b110 +
0Q
0S
0Z
0^
1"
1[
1$
1#
1%
#516000
za
0'
1_
1Z
0&
b110100 b
#520000
0%
#525000
06
09
1.
z4
0/
01
zX
1-
0$
0P
0V
b101 !
b101 +
1Q
1S
1%
#526000
b110101 b
#530000
0%
#535000
0X
0-
1P
zV
b100 !
b100 +
0Q
0S
1%
#536000
b110110 b
#540000
0%
#545000
0B
0E
1:
z@
0;
0=
z6
19
0.
04
1/
11
zX
1-
0P
0V
b11 !
b11 +
1Q
1S
1%
#546000
1'
b110111 b
#550000
0%
#555000
0X
0-
1P
zV
b10 !
b10 +
0Q
0S
0#
1%
#556000
1a
z_
0Z
1&
b111000 b
#560000
0%
#565000
06
09
1.
z4
0/
01
0`
zX
1-
1$
1Z
z^
0"
0[
0P
0V
b1 !
b1 +
1Q
1S
1#
1%
#566000
b111001 b
#570000
0%
#575000
0X
0-
z`
1P
zV
b0 !
b0 +
0Q
0S
0Z
0^
1"
1[
0#
1%
#576000
za
1_
1Z
0&
b111010 b
#580000
0%
#585000
zN
0F
0L
1G
1I
zB
1E
0:
0@
1;
1=
z6
19
0.
04
1/
11
zX
1-
0$
0P
0V
b1111 !
b1111 +
1Q
1S
1%
#586000
1a
0'
z_
0Z
1&
b111011 b
#590000
0%
#595000
0X
0-
0`
1P
zV
b1110 !
b1110 +
0Q
0S
1Z
z^
0"
0[
1$
1#
1%
#596000
za
0Z
1'
1_
0&
b111100 b
#600000
0%
#605000
06
09
1.
z4
0/
01
zX
1-
0$
0P
0V
b1101 !
b1101 +
1Q
1S
0#
1%
#606000
1a
1Z
0'
z_
1&
b111101 b
#610000
0%
#615000
0X
0-
z`
1P
zV
b1100 !
b1100 +
0Q
0S
0Z
0^
1"
1[
1$
1#
1%
#616000
1'
b111110 b
#620000
0%
#625000
0B
0E
1:
z@
0;
0=
z6
19
0.
04
1/
11
0`
zX
1-
1Z
z^
0"
0[
0P
0V
b1011 !
b1011 +
1Q
1S
0#
1%
#626000
b111111 b
#630000
0%
#635000
0X
0-
z`
1P
zV
b1010 !
b1010 +
0Q
0S
0Z
0^
1"
1[
1#
1%
#636000
za
0'
1_
1Z
0&
b1000000 b
#640000
0%
#645000
06
09
1.
z4
0/
01
zX
1-
0$
0P
0V
b1001 !
b1001 +
1Q
1S
1%
#646000
1'
b1000001 b
#650000
0%
#655000
0X
0-
1P
zV
b1000 !
b1000 +
0Q
0S
0#
1%
#656000
0'
b1000010 b
#660000
0%
#665000
0N
1F
zL
0G
0I
zB
1E
0:
0@
1;
1=
z6
19
0.
04
1/
11
zX
1-
0P
0V
b111 !
b111 +
1Q
1S
1%
#666000
1'
b1000011 b
#670000
0%
#675000
0X
0-
1P
zV
b110 !
b110 +
0Q
0S
1%
#676000
1a
0'
z_
0Z
1&
b1000100 b
#680000
0%
#685000
06
09
1.
z4
0/
01
0`
zX
1-
1$
1Z
z^
0"
0[
0P
0V
b101 !
b101 +
1Q
1S
1#
1%
#686000
za
0Z
1'
1_
0&
b1000101 b
#690000
0%
#695000
0X
0-
1P
zV
b100 !
b100 +
0Q
0S
0$
0#
1%
#696000
0'
b1000110 b
#700000
0%
#705000
0B
0E
1:
z@
0;
0=
z6
19
0.
04
1/
11
zX
1-
0P
0V
b11 !
b11 +
1Q
1S
1%
#706000
1'
b1000111 b
#710000
0%
#715000
0X
0-
1P
zV
b10 !
b10 +
0Q
0S
1%
#716000
0'
b1001000 b
#720000
0%
#725000
06
09
1.
z4
0/
01
zX
1-
0P
0V
b1 !
b1 +
1Q
1S
1%
#726000
1a
1Z
z_
1&
b1001001 b
#730000
0%
#735000
0X
0-
z`
1P
zV
b0 !
b0 +
0Q
0S
0Z
0^
1"
1[
1$
1#
1%
#736000
1'
b1001010 b
#740000
0%
#745000
zN
0F
0L
1G
1I
zB
1E
0:
0@
1;
1=
z6
19
0.
04
1/
11
0`
zX
1-
1Z
z^
0"
0[
0P
0V
b1111 !
b1111 +
1Q
1S
0#
1%
#746000
b1001011 b
#750000
0%
#755000
0X
0-
z`
1P
zV
b1110 !
b1110 +
0Q
0S
0Z
0^
1"
1[
1#
1%
#756000
0'
b1001100 b
#760000
0%
#765000
06
09
1.
z4
0/
01
0`
zX
1-
1Z
z^
0"
0[
0P
0V
b1101 !
b1101 +
1Q
1S
1%
#766000
za
0Z
1_
0&
b1001101 b
#770000
0%
#775000
0X
0-
1P
zV
b1100 !
b1100 +
0Q
0S
0$
1%
#776000
1a
1Z
z_
1&
b1001110 b
#780000
0%
#785000
0B
0E
1:
z@
0;
0=
z6
19
0.
04
1/
11
z`
zX
1-
1$
0Z
0^
1"
1[
0P
0V
b1011 !
b1011 +
1Q
1S
1%
#786000
za
1'
1_
1Z
0&
b1001111 b
#790000
0%
#795000
0X
0-
1P
zV
b1010 !
b1010 +
0Q
0S
0$
0#
1%
#796000
1a
0'
z_
0Z
1&
b1010000 b
#800000
0%
#805000
06
09
1.
z4
0/
01
0`
zX
1-
1$
1Z
z^
0"
0[
0P
0V
b1001 !
b1001 +
1Q
1S
1#
1%
#806000
za
0Z
1_
0&
b1010001 b
#810000
0%
#815000
0X
0-
1P
zV
b1000 !
b1000 +
0Q
0S
0$
1%
#816000
1a
1Z
1'
z_
1&
b1010010 b
#820000
0%
#825000
0N
1F
zL
0G
0I
zB
1E
0:
0@
1;
1=
z6
19
0.
04
1/
11
z`
zX
1-
1$
0Z
0^
1"
1[
0P
0V
b111 !
b111 +
1Q
1S
0#
1%
#826000
za
0'
1_
1Z
0&
b1010011 b
#830000
0%
#835000
0X
0-
1P
zV
b110 !
b110 +
0Q
0S
0$
1%
#836000
1'
b1010100 b
#840000
0%
#845000
06
09
1.
z4
0/
01
zX
1-
0P
0V
b101 !
b101 +
1Q
1S
1%
#846000
1a
0'
z_
0Z
1&
b1010101 b
#850000
0%
#855000
0X
0-
0`
1P
zV
b100 !
b100 +
0Q
0S
1Z
z^
0"
0[
1$
1#
1%
#856000
za
0Z
1_
0&
b1010110 b
#860000
0%
#865000
0B
0E
1:
z@
0;
0=
z6
19
0.
04
1/
11
zX
1-
0$
0P
0V
b11 !
b11 +
1Q
1S
1%
#866000
1a
1Z
z_
1&
b1010111 b
#870000
0%
#875000
0X
0-
z`
1P
zV
b10 !
b10 +
0Q
0S
0Z
0^
1"
1[
1$
1%
#876000
za
1'
1_
1Z
0&
b1011000 b
#880000
0%
#885000
06
09
1.
z4
0/
01
zX
1-
0$
0P
0V
b1 !
b1 +
1Q
1S
0#
1%
#886000
0'
b1011001 b
#890000
0%
#895000
0X
0-
1P
zV
b0 !
b0 +
0Q
0S
1%
#896000
1'
b1011010 b
#900000
0%
#905000
zN
0F
0L
1G
1I
zB
1E
0:
0@
1;
1=
z6
19
0.
04
1/
11
zX
1-
0P
0V
b1111 !
b1111 +
1Q
1S
1%
#906000
b1011011 b
#910000
0%
#915000
0X
0-
1P
zV
b1110 !
b1110 +
0Q
0S
1%
#916000
1a
0'
z_
0Z
1&
b1011100 b
#920000
0%
#925000
06
09
1.
z4
0/
01
0`
zX
1-
1$
1Z
z^
0"
0[
0P
0V
b1101 !
b1101 +
1Q
1S
1#
1%
#926000
za
0Z
1_
0&
b1011101 b
#930000
0%
#935000
0X
0-
1P
zV
b1100 !
b1100 +
0Q
0S
0$
1%
#936000
1'
b1011110 b
#940000
0%
#945000
0B
0E
1:
z@
0;
0=
z6
19
0.
04
1/
11
zX
1-
0P
0V
b1011 !
b1011 +
1Q
1S
0#
1%
#946000
0'
b1011111 b
#950000
0%
#955000
0X
0-
1P
zV
b1010 !
b1010 +
0Q
0S
1%
#956000
b1100000 b
#960000
0%
#965000
06
09
1.
z4
0/
01
zX
1-
0P
0V
b1001 !
b1001 +
1Q
1S
1%
#966000
1a
1Z
1'
z_
1&
b1100001 b
#970000
0%
#975000
0X
0-
z`
1P
zV
b1000 !
b1000 +
0Q
0S
0Z
0^
1"
1[
1$
1#
1%
#976000
0'
b1100010 b
#980000
0%
#985000
0N
1F
zL
0G
0I
zB
1E
0:
0@
1;
1=
z6
19
0.
04
1/
11
0`
zX
1-
1Z
z^
0"
0[
0P
0V
b111 !
b111 +
1Q
1S
1%
#986000
1'
b1100011 b
#990000
0%
#995000
0X
0-
z`
1P
zV
b110 !
b110 +
0Q
0S
0Z
0^
1"
1[
0#
1%
#996000
0'
b1100100 b
#1000000
0%
#1005000
06
09
1.
z4
0/
01
0`
zX
1-
1Z
z^
0"
0[
0P
0V
b101 !
b101 +
1Q
1S
1#
1%
#1006000
b1100101 b
#1010000
0%
#1015000
0X
0-
z`
1P
zV
b100 !
b100 +
0Q
0S
0Z
0^
1"
1[
1%
#1020000
0%
#1025000
0B
0E
1:
z@
0;
0=
z6
19
0.
04
1/
11
0`
zX
1-
1Z
z^
0"
0[
0P
0V
b11 !
b11 +
1Q
1S
1%
#1030000
0%
#1035000
0X
0-
z`
1P
zV
b10 !
b10 +
0Q
0S
0Z
0^
1"
1[
1%
#1040000
0%
#1045000
06
09
1.
z4
0/
01
0`
zX
1-
1Z
z^
0"
0[
0P
0V
b1 !
b1 +
1Q
1S
1%
#1050000
0%
#1055000
0X
0-
z`
1P
zV
b0 !
b0 +
0Q
0S
0Z
0^
1"
1[
1%
#1060000
0%
#1065000
zN
0F
0L
1G
1I
zB
1E
0:
0@
1;
1=
z6
19
0.
04
1/
11
0`
zX
1-
1Z
z^
0"
0[
0P
0V
b1111 !
b1111 +
1Q
1S
1%
#1070000
0%
#1075000
0X
0-
z`
1P
zV
b1110 !
b1110 +
0Q
0S
0Z
0^
1"
1[
1%
#1080000
0%
#1085000
06
09
1.
z4
0/
01
0`
zX
1-
1Z
z^
0"
0[
0P
0V
b1101 !
b1101 +
1Q
1S
1%
#1090000
0%
#1095000
0X
0-
z`
1P
zV
b1100 !
b1100 +
0Q
0S
0Z
0^
1"
1[
1%
#1100000
0%
#1105000
0B
0E
1:
z@
0;
0=
z6
19
0.
04
1/
11
0`
zX
1-
1Z
z^
0"
0[
0P
0V
b1011 !
b1011 +
1Q
1S
1%
#1110000
0%
#1115000
0X
0-
z`
1P
zV
b1010 !
b1010 +
0Q
0S
0Z
0^
1"
1[
1%
#1120000
0%
#1125000
06
09
1.
z4
0/
01
0`
zX
1-
1Z
z^
0"
0[
0P
0V
b1001 !
b1001 +
1Q
1S
1%
#1130000
0%
#1135000
0X
0-
z`
1P
zV
b1000 !
b1000 +
0Q
0S
0Z
0^
1"
1[
1%
#1140000
0%
