Divide_by_3/rtl/div_by_3.sv
///////////////////////////////////////////////////////////////////////////////////
///                            Divide By 3                                      ///
///                                                                             ///
///////////////////////////////////////////////////////////////////////////////////
///   This project designs an FSM in Verilog that will essentially generate as  ///
///   output the reminder of a serial bit stream inputted MSB first when divided///
///    by 3.                                                                    ///
///                                                                             ///
///   Copyright 2025 Ujval Madhu, All rights reserved                           ///
///////////////////////////////////////////////////////////////////////////////////
//  CVS Log
//
//  Id: div_by_3.v, v 1.0
//
//  $Date: 2024-15-04
//  $Revision: 1.0 $
//  $Author:  Ujval Madhu

module div_by_3(
    input logic clk,
    input logic rst,
    input logic in,
    output logic [1:0] out_r
);

    typedef enum bit[1:0] {SA0, SA1, SA2} state_t;
    bit [1:0] current_state;
    bit [1:0] next_state;


// Current State Logic:

    always_ff@(posedge clk) begin
        
        if(rst) begin
            current_state <= SA0;
        end
        else begin
            current_state <= next_state;
        end

    end

// Next State Logic:
    always_comb begin
        
        case(current_state)
            SA0: begin
                    if(in == 0) begin
                        next_state = SA0;
                    end
                    else if(in == 1) begin
                        next_state = SA1;
                    end
                end
            
            SA1: begin
                    if(in == 0) begin
                        next_state = SA2;
                    end
                    else if(in == 1) begin
                        next_state = SA0;
                    end
                end
            SA2: begin
                    if(in == 0) begin
                        next_state = SA1;
                    end
                    else if(in == 1) begin
                        next_state = SA2;
                    end
                end
            default: next_state = SA0;
        endcase
    end


// Output Logic:
    always_ff@(posedge clk) begin
        case(current_state)
            SA0: out_r <= 2'b00;
            SA1: out_r <= 2'b01;
            SA2: out_r <= 2'b10;
            default: out_r <= 2'b00;
        endcase
    end

endmodule

Divide_by_3/rtl/testbench.sv
///////////////////////////////////////////////////////////////////////////////////
///       Switch Level Modeling of a CMOS Gates and Boolean Logic               ///
///                                                                             ///
///////////////////////////////////////////////////////////////////////////////////
///   Testbench Module                                                          ///
///                                                                             ///
///   Copyright 2025 Ujval Madhu, All rights reserved                           ///
///////////////////////////////////////////////////////////////////////////////////
//  CVS Log
//
//  Id: testbench.sv, v 1.0
//
//  $Date: 2024-07-03
//  $Revision: 1.0 $
//  $Author:  Ujval Madhu

module testbench;
    logic in_a;
    logic clk;
    logic rst;
    int seed;

    logic [1:0] out;
    logic [1:0] out_buf1;
    logic [1:0] out_buf2;

    logic in_buf1;
    logic in_buf2;
    logic in_buf3;


    initial begin
        clk = 1'b0;
        repeat(100) begin
            #5 clk = ~clk;     
        end
    end


    // Instantiating DUT
    div_by_3 dut(.clk(clk), .rst(rst), .in(in_a), .out_r(out));

    always @(posedge clk) begin
        out_buf1 <= out;
        out_buf2 <= out_buf1;
        in_buf1 <= in_a;
        in_buf2 <= in_buf1;
        in_buf3 <= in_buf2;
    end

    // Random Stimulus Generation
    initial begin
        seed = $random;
        $random(seed);              // Icarus doesn't support $srandom yet

        in_a = 1'b0;
        rst  = 1'b1; 
        #10;
        rst = 1'b0;
        
        for(int i = 1; i <= 20; i++) begin
            in_a = $urandom_range(0,1);

            #10;
            
            $display("DUT Signals: Reset: %d, Input bit: %b, Reminder: %d, ", rst, in_buf2, out);

            //Verification
            
            if(!rst) begin
                if (out_buf1 == 0 && in_buf2 == 0 && out != 0) begin
                    $display("Error Detected on DUT at %t, Previous Reminder: %0d, Input bit: %b, Reminder: %d",$time, out_buf1, in_buf2, out); 
                    $fatal;
                end
                if (out_buf1 == 0 && in_buf2 == 1 && out != 1) begin
                    $display("Error Detected on DUT at %t, Previous Reminder: %0d, Input bit: %b, Reminder: %d",$time, out_buf1, in_buf2, out); 
                    $fatal;
                end

                if (out_buf1 == 1 && in_buf2 == 0 && out != 2) begin
                    $display("Error Detected on DUT at %t, Previous Reminder: %0d, Input bit: %b, Reminder: %d",$time, out_buf1, in_buf2, out); 
                    $fatal;
                end
                if (out_buf1 == 1 && in_buf2 == 1 && out != 0) begin
                    $display("Error Detected on DUT at %t, Previous Reminder: %0d, Input bit: %b, Reminder: %d",$time, out_buf1, in_buf2, out); 
                    $fatal;
                end  

                if (out_buf1 == 2 && in_buf2 == 0 && out != 1) begin
                    $display("Error Detected on DUT at %t, Previous Reminder: %0d, Input bit: %b, Reminder: %d",$time, out_buf1, in_buf2, out); 
                    $fatal;
                end
                if (out_buf1 == 2 && in_buf2 == 1 && out != 2) begin
                    $display("Error Detected on DUT at %t, Previous Reminder: %0d, Input bit: %b, Reminder: %d",$time, out_buf1, in_buf2, out); 
                    $fatal;
                end                                              

            end
        end

        $display("All Test Cases Passed!!\n");
        $finish;
    end

    // Generating Waveform Files
    initial begin
        $dumpfile("testbench.vcd");
        $dumpvars(0, testbench);
    end

endmodule

Divide_by_3/waves/testbench.vcd
$date
	Wed Apr 16 08:59:55 2025
$end
$version
	Icarus Verilog
$end
$timescale
	1ps
$end
$scope module testbench $end
$var wire 2 ! out [1:0] $end
$var reg 1 " clk $end
$var reg 1 # in_a $end
$var reg 1 $ in_buf1 $end
$var reg 1 % in_buf2 $end
$var reg 1 & in_buf3 $end
$var reg 2 ' out_buf1 [1:0] $end
$var reg 2 ( out_buf2 [1:0] $end
$var reg 1 ) rst $end
$var integer 32 * seed [31:0] $end
$scope module dut $end
$var wire 1 " clk $end
$var wire 1 # in $end
$var wire 1 ) rst $end
$var reg 2 + out_r [1:0] $end
$var reg 2 , current_state [1:0] $end
$var reg 2 - next_state [1:0] $end
$upscope $end
$scope begin $ivl_for_loop0 $end
$var integer 32 . i [31:0] $end
$upscope $end
$upscope $end
$enddefinitions $end
$comment Show the parameter values. $end
$dumpall
$end
#0
$dumpvars
b0 .
b0 -
b0 ,
bx +
b11000011110100100110000111010101 *
1)
bx (
bx '
x&
x%
x$
0#
0"
bx !
$end
#5000
b0 !
b0 +
0$
1"
#10000
b1 -
0"
1#
b1 .
0)
#15000
b0 -
0%
1$
b0 '
b1 ,
1"
#20000
b10 -
0"
0#
b10 .
#25000
b1 -
b10 ,
b1 !
b1 +
0&
1%
0$
b0 (
1"
#30000
0"
b11 .
#35000
b10 -
1&
0%
b1 '
b10 !
b10 +
b1 ,
1"
#40000
0"
b100 .
#45000
b1 -
b10 ,
b1 !
b1 +
0&
b1 (
b10 '
1"
#50000
b10 -
0"
1#
b101 .
#55000
1$
b10 (
b1 '
b10 !
b10 +
1"
#60000
0"
b110 .
#65000
1%
b1 (
b10 '
1"
#70000
b1 -
0"
0#
b111 .
#75000
b10 -
1&
0$
b10 (
b1 ,
1"
#80000
0"
b1000 .
#85000
b1 -
b10 ,
b1 !
b1 +
0%
1"
#90000
b10 -
0"
1#
b1001 .
#95000
0&
1$
b1 '
b10 !
b10 +
1"
#100000
0"
b1010 .
#105000
1%
b1 (
b10 '
1"
#110000
0"
b1011 .
#115000
1&
b10 (
1"
#120000
0"
b1100 .
#125000
1"
#130000
0"
b1101 .
#135000
1"
#140000
0"
b1110 .
#145000
1"
#150000
0"
b1111 .
#155000
1"
#160000
b1 -
0"
0#
b10000 .
#165000
b10 -
b1 ,
0$
1"
#170000
0"
b10001 .
#175000
b1 -
0%
b1 !
b1 +
b10 ,
1"
#180000
0"
b10010 .
#185000
b10 -
b1 ,
b10 !
b10 +
0&
b1 '
1"
#190000
b0 -
0"
1#
b10011 .
#195000
b1 -
1$
b1 (
b10 '
b1 !
b1 +
b0 ,
1"
#200000
b0 -
0"
0#
b10100 .
#205000
b0 !
b0 +
1%
0$
b10 (
b1 '
1"
#210000
0"
b10101 .
