Dataflow_Modeling/rtl/decoder_2x4.v
///////////////////////////////////////////////////////////////////////////////////
///                    2x4 Decoder using Data Flow Modeling                     ///
///                                                                             ///
///////////////////////////////////////////////////////////////////////////////////
///   2x4 Decoder Module: In this design we are primarily using NAND or NOR     ///
///                  gates for logic realization using Dataflow modeling        ///
///                  Although most ASIC tools optimize for this and is not      /// 
///                  required in FPGA design                                    ///
///                                                                             ///
///   Copyright 2025 Ujval Madhu, All rights reserved                           ///
///////////////////////////////////////////////////////////////////////////////////
//  CVS Log
//
//  Id: decoder_2x4.v, v 1.0
//
//  $Date: 2024-11-03
//  $Revision: 1.0 $
//  $Author:  Ujval Madhu

module decoder_2x4(
    input a,
    input b,
    input en,
    output [3:0] out
);

assign  out[0] = en & ~( a | b ) ,        // out0 = en.a'.b'
        out[1] = en & ~( a | ~b ),        // out1 = en.a'.b
        out[2] = en & ~( ~a | b ),        // out1 = en.a.b' 
        out[3] = en & ~( ~a | ~b );       // out1 = en.a.b 

endmodule

Dataflow_Modeling/rtl/mux_2x1.v
/////////////////////////////////////////////////////////////////////////////////////
///                    2x1 Mux using Data Flow Modeling                           ///
///                                                                               ///
/////////////////////////////////////////////////////////////////////////////////////
///   2x1MUX Module: In this design we are primarily using NAND or NOR operations ///
///                  for logic realization using Dataflow modeling                ///
///                                                                               ///
///   Copyright 2025 Ujval Madhu, All rights reserved                             ///
/////////////////////////////////////////////////////////////////////////////////////
//  CVS Log
//
//  Id: mux_2x1.v, v 1.0
//
//  $Date: 2024-11-03
//  $Revision: 1.0 $
//  $Author:  Ujval Madhu

module mux_2x1(
    input a,
    input b,
    input sel,
    output out
);

assign out = ( a & ~sel ) | ( b & sel );

endmodule

Dataflow_Modeling/rtl/testbench.sv
///////////////////////////////////////////////////////////////////////////////////
///       Switch Level Modeling of a CMOS Gates and Boolean Logic               ///
///                                                                             ///
///////////////////////////////////////////////////////////////////////////////////
///   Testbench Module                                                          ///
///                                                                             ///
///   Copyright 2025 Ujval Madhu, All rights reserved                           ///
///////////////////////////////////////////////////////////////////////////////////
//  CVS Log
//
//  Id: testbench.sv, v 1.0
//
//  $Date: 2024-07-03
//  $Revision: 1.0 $
//  $Author:  Ujval Madhu

module testbench;
    reg in_a, in_b;
    reg sel;
    reg en;
    wire out_m;
    wire [3:0] out_d;
    integer seed;

    // Instantiating 2x1 MUX
    mux_2x1 m1(.a(in_a), .b(in_b), .sel(sel), .out(out_m));

    // Instantiating 2x4 Decoder
    decoder_2x4 d1(.a(in_a), .b(in_b), .en(en), .out(out_d));

    // Random Stimulus Generation
    initial begin
        seed = $random;
        $random(seed);              // Icarus doesn't support $srandom yet

        in_b = 1'b0;
        in_a = 1'b0;
        sel  = 1'b0;
        en   = 1'b0;

        #10;
        
        for(int i = 1; i <= 10; i++) begin
            in_a = $random % 2;
            in_b = $random % 2;
            sel  = $random % 2;
            en   = $random % 2;

            #10;
            
            $display("2x1 MUX Output: Input A: %b, Input B: %b, Sel: %b, Out: %b", in_a, in_b, sel, out_m);
            $display("2x4 Decoder Output: Input A: %b, Input B: %b, En: %b, Out: %b", in_a, in_b, en, out_d);
            
            //#10
            // Verification
            // // Inverter
            // if (sel == ) begin
            //     $display("Error Detected on inverter at %t, output = %b input = %b",$time, out_inv, in); 
            //     $fatal;
            // end

            // // NAND
            // if (out_nand != ~(in_a & in_b) ) begin
            //     $display("Error Detected on NAND at %t, Output = %b , Input A= %b, Input B = %b",$time, out_nand, in_a, in_b); 
            //     $fatal;
            // end
        end
    end

    // Generating Waveform Files
    initial begin
        $dumpfile("testbench.vcd");
        $dumpvars(0, testbench);
    end

endmodule

Dataflow_Modeling/waves/testbench.vcd
$date
	Tue Mar 11 09:32:19 2025
$end
$version
	Icarus Verilog
$end
$timescale
	1ps
$end
$scope module testbench $end
$var wire 1 ! out_m $end
$var wire 4 " out_d [3:0] $end
$var reg 1 # en $end
$var reg 1 $ in_a $end
$var reg 1 % in_b $end
$var reg 1 & sel $end
$var integer 32 ' seed [31:0] $end
$scope module d1 $end
$var wire 1 $ a $end
$var wire 1 % b $end
$var wire 1 # en $end
$var wire 4 ( out [3:0] $end
$upscope $end
$scope module m1 $end
$var wire 1 $ a $end
$var wire 1 % b $end
$var wire 1 ! out $end
$var wire 1 & sel $end
$upscope $end
$scope begin $ivl_for_loop0 $end
$var integer 32 ) i [31:0] $end
$upscope $end
$upscope $end
$enddefinitions $end
$comment Show the parameter values. $end
$dumpall
$end
#0
$dumpvars
b0 )
b0 (
b11000011110100100110000111010101 '
0&
0%
0$
0#
b0 "
0!
$end
#10000
1!
b1000 "
b1000 (
1#
1&
1%
1$
b1 )
#20000
1!
0&
b10 )
#30000
0!
b100 "
b100 (
1&
0%
b11 )
#40000
b10 "
b10 (
0&
1%
0$
b100 )
#50000
1!
b0 "
b0 (
0#
1&
b101 )
#60000
1!
0&
0%
1$
b110 )
#70000
0!
b100 "
b100 (
1#
1&
b111 )
#80000
1!
b0 "
b0 (
0#
0&
1%
b1000 )
#90000
0!
1&
0%
0$
b1001 )
#100000
1!
b1000 "
b1000 (
1#
1%
1$
b1010 )
#110000
b1011 )
