Modelling_CMOS_Gates/rtl/xnor.v
///////////////////////////////////////////////////////////////////////////////////
///             Switch Level Modeling of a CMOS NAND Gate                       ///
///                                                                             ///
///////////////////////////////////////////////////////////////////////////////////
///   Nand Module:                                                              ///
///                                                                             ///
///   Copyright 2025 Ujval Madhu, All rights reserved                           ///
///////////////////////////////////////////////////////////////////////////////////
//  CVS Log
//
//  Id: nand.v, v 1.0
//
//  $Date: 2024-07-03
//  $Revision: 1.0 $
//  $Author:  Ujval Madhu

module cmos_xnor(
    input in_a,
    input in_b,
    output out
);
    supply1 vdd;
    supply0 gnd;
    wire w1p, w2p, w3n,w4n;

    // Argument order (Drain, Source, gate)
    // PMOS A.B + A'.B' 
    pmos p1(w2p, vdd, in_b);
    pmos p2(out, w1p, in_a);

    pmos p3(w2n, vdd, ~in_b);
    pmos p4(out, w2n, ~in_a);

    // NMOS A.B' + A'.B ; complement of the PMOS structure
    nmos n1(w1n, gnd, in_a);
    nmos n2(out, w1n, ~in_b);

    nmos n3(w2n, gnd, ~in_a);
    nmos n4(out, w2n, in_b);

endmodule

Modelling_CMOS_Gates/rtl/xor.v
///////////////////////////////////////////////////////////////////////////////////
///             Switch Level Modeling of a CMOS XOR Gate                       ///
///                                                                             ///
///////////////////////////////////////////////////////////////////////////////////
///   XOR Module:                                                              ///
///                                                                             ///
///   Copyright 2025 Ujval Madhu, All rights reserved                           ///
///////////////////////////////////////////////////////////////////////////////////
//  CVS Log
//
//  Id: xor.v, v 1.0
//
//  $Date: 2024-07-03
//  $Revision: 1.0 $
//  $Author:  Ujval Madhu

module cmos_xor(
    input in_a,
    input in_b,
    output out
);
    supply1 vdd;
    supply0 gnd;
    wire w1p, w2p, w3n,w4n;

    // Argument order (Drain, Source, gate)
    // PMOS A.B' + A'.B
    pmos p1(w1p, vdd, in_a);
    pmos p2(out, w1p, ~in_b);

    pmos p3(w2p, vdd, ~in_a);
    pmos p4(out, w2p, in_b);

    // NMOS A.B + A'.B' ; complement of the PMOS structure
    nmos n1(w2n, gnd, in_b);
    nmos n2(out, w1n, in_a);

    nmos n3(w2p, gnd, ~in_b);
    nmos n4(out, w2p, ~in_a);

endmodule

Modelling_CMOS_Gates/rtl/nor.v
///////////////////////////////////////////////////////////////////////////////////
///             Switch Level Modeling of a CMOS NOR Gate                        ///
///                                                                             ///
///////////////////////////////////////////////////////////////////////////////////
///   NOR Module:                                                               ///
///                                                                             ///
///   Copyright 2025 Ujval Madhu, All rights reserved                           ///
///////////////////////////////////////////////////////////////////////////////////
//  CVS Log
//
//  Id: nor.v, v 1.0
//
//  $Date: 2024-07-03
//  $Revision: 1.0 $
//  $Author:  Ujval Madhu

module cmos_nor(
    input in_a,
    input in_b,
    output out
);

    wire w1;
    supply0 gnd;
    supply1 vdd;

    // Argument order (Drain, Source, gate)
    // PMOS in series
    pmos p1(w1, vdd, in_a);                    
    pmos p2(out, w1, in_b);

    // NMOS in parallel
    nmos n1(out, gnd, in_a);
    nmos n2(out, gnd, in_b);

endmodule

Modeling_CMOS_Gates/rtl/nand.v
///////////////////////////////////////////////////////////////////////////////////
///             Switch Level Modeling of a CMOS NAND Gate                       ///
///                                                                             ///
///////////////////////////////////////////////////////////////////////////////////
///   Nand Module:                                                              ///
///                                                                             ///
///   Copyright 2025 Ujval Madhu, All rights reserved                           ///
///////////////////////////////////////////////////////////////////////////////////
//  CVS Log
//
//  Id: nand.v, v 1.0
//
//  $Date: 2024-07-03
//  $Revision: 1.0 $
//  $Author:  Ujval Madhu

module cmos_nand(
    input in_a,
    input in_b,
    output out
);
    supply1 vdd;
    supply0 gnd;
    wire w1;

    // Argument order (Drain, Source, gate)
    // PMOS in Parallel
    pmos p1(out, vdd, in_a);
    pmos p2(out, vdd, in_b);

    // NMOS in Series
    nmos n1(w1, gnd, in_b);
    nmos n2(out, w1, in_a);
endmodule

Modeling_CMOS_Gates/rtl/inverter.v
///////////////////////////////////////////////////////////////////////////////////
///             Switch Level Modeling of a CMOS Inverter                        ///
///                                                                             ///
///////////////////////////////////////////////////////////////////////////////////
///   Inverter Module:                                                          ///
///                                                                             ///
///   Copyright 2025 Ujval Madhu, All rights reserved                           ///
///////////////////////////////////////////////////////////////////////////////////
//  CVS Log
//
//  Id: inverter.v, v 1.0
//
//  $Date: 2024-07-03
//  $Revision: 1.0 $
//  $Author:  Ujval Madhu

module cmos_inv(
    input in,
    output out
);
supply1 vdd;
supply0 gnd;

// Argument order (Drain, Source, gate)
nmos n1(out, gnd, in);
pmos p1(out, vdd, in);

endmodule

Modelling_CMOS_Gates/rtl/testbench.sv
///////////////////////////////////////////////////////////////////////////////////
///       Switch Level Modeling of a CMOS Gates and Boolean Logic               ///
///                                                                             ///
///////////////////////////////////////////////////////////////////////////////////
///   Testbench Module                                                          ///
///                                                                             ///
///   Copyright 2025 Ujval Madhu, All rights reserved                           ///
///////////////////////////////////////////////////////////////////////////////////
//  CVS Log
//
//  Id: testbench.sv, v 1.0
//
//  $Date: 2024-07-03
//  $Revision: 1.0 $
//  $Author:  Ujval Madhu

module testbench;
    reg in;
    reg in_a, in_b;
    wire out_inv;
    wire out_nand;
    wire out_nor;
    wire out_xor;
    wire out_xnor;
    integer seed;

    // Instantiating Inverter
    cmos_inv inv1(.in(in), .out(out_inv));

    // Instantiating NAND Gate
    cmos_nand nand1(.in_a(in_a),.in_b(in_b), .out(out_nand));

    // Instantiating NOR Gate
    cmos_nor nor1(.in_a(in_a),.in_b(in_b), .out(out_nor));

    // Instantiating NOR Gate
    cmos_xor xor1(.in_a(in_a),.in_b(in_b), .out(out_xor));

    // Instantiating NOR Gate
    cmos_xnor xnor1(.in_a(in_a),.in_b(in_b), .out(out_xnor));

    // Random Stimulus Generation
    initial begin
        seed = $random;
        $random(seed);              // Icarus doesn't support $srandom yet

        in = 1'b0;
        in_b = 1'b0;
        in_a = 1'b0;
        #10;
        
        for(int i = 1; i <= 10; i++) begin
            in = $random % 2;
            in_a = $random % 2;
            in_b = $random % 2;
            #10;
            $display("-----------Test %0d---------- @ %0t", i, $time);
            $display("Inverter: Input: %b, Output: %b", in, out_inv);
            $display("NAND: Input A: %b, Input B: %b, Output: %b", in_a, in_b, out_nand);
            $display("NOR: Input A: %b, Input B: %b, Output: %b", in_a, in_b, out_nor);
            $display("XOR: Input A: %b, Input B: %b, Output: %b", in_a, in_b, out_xor);
            $display("XNOR: Input A: %b, Input B: %b, Output: %b", in_a, in_b, out_xnor);
            
            #10
            // Verification
            // Inverter
            if (out_inv != ~in) begin
                $display("Error Detected on inverter at %t, output = %b input = %b",$time, out_inv, in); 
                $fatal;
            end

            // NAND
            if (out_nand != ~(in_a & in_b) ) begin
                $display("Error Detected on NAND at %t, Output = %b , Input A= %b, Input B = %b",$time, out_nand, in_a, in_b); 
                $fatal;
            end

            // NOR
            if (out_nor != ~(in_a | in_b) ) begin
                $display("Error Detected on NOR at %t, Output = %b , Input A = %b, Input B = %b",$time, out_nor, in_a, in_b); 
                $fatal;
            end

            // XOR
            if (out_xor != (in_a ^ in_b) ) begin
                $display("Error Detected on XOR at %t, Output = %b , Input A = %b, Input B = %b",$time, out_xor, in_a, in_b); 
                $fatal;
            end

            // XNOR
            if (out_xnor != ~(in_a ^ in_b) ) begin
                $display("Error Detected on XNOR at %t, Output = %b , Input A = %b, Input B = %b",$time, out_xnor, in_a, in_b); 
                $fatal;
            end
        end
    end

    // Generating Waveform Files
    initial begin
        $dumpfile("testbench.vcd");
        $dumpvars(0, testbench);
    end

endmodule

Modelling_CMOS_Gates/waves/testbench.vcd
$date
	Sat Mar  8 10:04:01 2025
$end
$version
	Icarus Verilog
$end
$timescale
	1ps
$end
$scope module testbench $end
$var wire 1 ! out_inv $end
$var wire 1 " out_nand $end
$var wire 1 # out_nor $end
$var wire 1 $ out_xnor $end
$var wire 1 % out_xor $end
$var reg 1 & in $end
$var reg 1 ' in_a $end
$var reg 1 ( in_b $end
$var integer 32 ) seed [31:0] $end
$scope module inv1 $end
$var wire 1 * gnd $end
$var wire 1 & in $end
$var wire 1 ! out $end
$var wire 1 + vdd $end
$upscope $end
$scope module nand1 $end
$var wire 1 , gnd $end
$var wire 1 ' in_a $end
$var wire 1 ( in_b $end
$var wire 1 " out $end
$var wire 1 - vdd $end
$var wire 1 . w1 $end
$upscope $end
$scope module nor1 $end
$var wire 1 / gnd $end
$var wire 1 ' in_a $end
$var wire 1 ( in_b $end
$var wire 1 # out $end
$var wire 1 0 vdd $end
$var wire 1 1 w1 $end
$upscope $end
$scope module xnor1 $end
$var wire 1 2 gnd $end
$var wire 1 ' in_a $end
$var wire 1 ( in_b $end
$var wire 1 $ out $end
$var wire 1 3 vdd $end
$var wire 1 4 w1n $end
$var wire 1 5 w1p $end
$var wire 1 6 w2n $end
$var wire 1 7 w2p $end
$upscope $end
$scope module xor1 $end
$var wire 1 8 gnd $end
$var wire 1 ' in_a $end
$var wire 1 ( in_b $end
$var wire 1 % out $end
$var wire 1 9 vdd $end
$var wire 1 : w1n $end
$var wire 1 ; w1p $end
$var wire 1 < w2n $end
$var wire 1 = w2p $end
$upscope $end
$scope begin $ivl_for_loop0 $end
$var integer 32 > i [31:0] $end
$upscope $end
$upscope $end
$enddefinitions $end
$comment Show the parameter values. $end
$dumpall
$end
#0
$dumpvars
b0 >
0=
z<
1;
z:
19
08
17
06
z5
z4
13
02
11
10
0/
z.
1-
0,
1+
0*
b11000011110100100110000111010101 )
0(
0'
0&
0%
z$
1#
1"
1!
$end
#10000
16
1=
z%
0"
0.
z7
0<
1(
z1
0#
1$
04
z;
1'
0!
1&
b1 >
#30000
b10 >
#50000
1!
0&
b11 >
#70000
b100 >
#90000
z6
0$
x=
1"
z.
17
x%
z<
0(
b101 >
#110000
x6
z=
0.
z7
1%
0<
1(
11
0#
x$
z4
1;
0'
0!
1&
b110 >
#130000
b111 >
#150000
06
0%
0=
z.
1#
17
z$
z<
0(
1!
0&
b1000 >
#170000
x6
1%
z=
0.
0#
z7
x$
0<
1(
0!
1&
b1001 >
#190000
1$
16
1=
0"
z1
04
z%
z;
1'
b1010 >
#210000
b1011 >
