Hands_on_RTL/Atomic_Counters/rtl/atm_counter.v
///////////////////////////////////////////////////////////////////////////////////
///                                                                             /// 
///                   64-Bit Atomic Counter with 32-Bit Bus                     ///
///                                                                             ///
///////////////////////////////////////////////////////////////////////////////////
/// A 64-bit event counter module and its 32-bit bus interface for a            ///
/// micro-controller. The counter increments on a trigger input, sends the      ///
/// counter value over through the bus in 2 single cycle atomic reads and       ///
/// issues an ack for each read. Two req must be asserted for completely        ///
/// reading the 64 bit counter value using the 32 bit bus.                      ///
///                                                                             ///
///   Copyright 2025 Ujval Madhu, All rights reserved                           ///
///////////////////////////////////////////////////////////////////////////////////
//  CVS Log
//
//  Id: atm_counter.v, v 1.0
//
//  $Date: 2024-19-04
//  $Revision: 1.0 $
//  $Author:  Ujval Madhu

module atm_counter(
    input clk,
    input rst,
    input trig_i,
    input req_i,
    input atomic_i,

    output reg ack_o,
    output reg[31:0] count_o
);

reg [63:0] count_reg;
reg [31:0] count_MSB;

always @(posedge clk or posedge rst) begin  
    if(rst)  begin count_reg <= 64'b0; end
    else if(trig_i) begin
        count_reg[63:0] <= count_reg[63:0] + 1'b1;
    end    
    else begin
        count_reg[63:0] <= count_reg[63:0];
    end
end

// Logic for ack_o
always @(posedge clk or posedge rst) begin
    if(rst) begin
        ack_o <= 1'b0;
    end
    else if(req_i) begin
        ack_o <= 1'b1;
    end
    else begin
        ack_o <= 1'b0;
    end
end


// Output MSB so that we dont get an incremented MSB for a non incremented LSB
always @(posedge clk or negedge rst) begin
    if(rst) begin
        count_MSB <= 32'd0;
    end
    else begin
        count_MSB <= count_reg[63:32];
    end
end


// Output logic
always @(posedge clk or negedge rst) begin
    if(rst) begin
        count_o[31:0] <= 32'd0;
    end
    if(req_i && atomic_i) begin
        count_o[31:0] <=  count_reg[31:0];
    end
    else if(req_i) begin
        count_o[31:0] <= count_MSB[31:0];
    end
    else begin
        count_o[31:0] <= 32'd0;
    end
end

endmodule

Hands_on_RTL/Atomic_Counters/rtl/testbench.sv
///////////////////////////////////////////////////////////////////////////////////
///            64-Bit Atomic Counter with 32-Bit Bus Testbench                  ///
///                                                                             ///
///////////////////////////////////////////////////////////////////////////////////
///   Testbench Module                                                          ///
///                                                                             ///
///   Copyright 2025 Ujval Madhu, All rights reserved                           ///
///////////////////////////////////////////////////////////////////////////////////
//  CVS Log
//
//  Id: testbench.sv, v 1.0
//
//  $Date: 2024-07-03
//  $Revision: 1.0 $
//  $Author:  Ujval Madhu

module testbench;
    reg atomic_i, req_i, trig_i;
    reg clk, rst;
    wire ack_o;
    wire [31:0] count_o;
    int seed;

    // Instantiating atmoic_counter
    atm_counter a1(.clk(clk), .rst(rst), .trig_i(trig_i), .req_i(req_i), .atomic_i(atomic_i), .ack_o(ack_o), .count_o(count_o));

    // Clock Gen
    initial begin
        clk = 1'b0;
        repeat(500) #5 clk = ~clk;
    end

    // Reset Gen
    initial begin
        rst = 1'b0;
        repeat(2) @(posedge clk);
        rst = 1'b1;
        repeat(2) @(posedge clk);
        rst = 1'b0;
    end

    // Random Stimulus Generation
    initial begin
        seed = $random;
        $random(seed);              // Icarus doesn't support $srandom yet

        trig_i      = 1'b0;
        atomic_i    = 1'b0;
        req_i       = 1'b0;
        #10;
        
        for(int i = 1; i <= 50; i++) begin

            @(posedge clk)
            trig_i      = $urandom_range(0,1);
            atomic_i    = $urandom_range(0,1);
            req_i       = $urandom_range(0,1);

            #1;
            
            $display("Atmoic Counter, Reset: %0b, Output: Trig_i: %b, Atomic_i: %b, req_i: %b, Count_o: %d, ack_o: %b", rst, trig_i, atomic_i, req_i, count_o, ack_o);

            //#10
            // Verification
            // // Inverter
            // if (sel == ) begin
            //     $display("Error Detected on inverter at %t, output = %b input = %b",$time, out_inv, in); 
            //     $fatal;
            // end

            // // NAND
            // if (out_nand != ~(in_a & in_b) ) begin
            //     $display("Error Detected on NAND at %t, Output = %b , Input A= %b, Input B = %b",$time, out_nand, in_a, in_b); 
            //     $fatal;
            // end
        end
    end

    // Generating Waveform Files
    initial begin
        $dumpfile("testbench.vcd");
        $dumpvars(0, testbench);
    end

endmodule

Hands_on_RTL/Atomic_Counters/waves/testbench.vcd
$date
	Sat Apr 26 10:47:56 2025
$end
$version
	Icarus Verilog
$end
$timescale
	1ps
$end
$scope module testbench $end
$var wire 32 ! count_o [31:0] $end
$var wire 1 " ack_o $end
$var reg 1 # atomic_i $end
$var reg 1 $ clk $end
$var reg 1 % req_i $end
$var reg 1 & rst $end
$var reg 1 ' trig_i $end
$var integer 32 ( seed [31:0] $end
$scope module a1 $end
$var wire 1 # atomic_i $end
$var wire 1 $ clk $end
$var wire 1 % req_i $end
$var wire 1 & rst $end
$var wire 1 ' trig_i $end
$var reg 1 " ack_o $end
$var reg 32 ) count_MSB [31:0] $end
$var reg 32 * count_o [31:0] $end
$var reg 64 + count_reg [63:0] $end
$upscope $end
$scope begin $ivl_for_loop0 $end
$var integer 32 , i [31:0] $end
$upscope $end
$upscope $end
$enddefinitions $end
$comment Show the parameter values. $end
$dumpall
$end
#0
$dumpvars
b0 ,
bx +
b0 *
bx )
b11000011110100100110000111010101 (
0'
0&
0%
0$
0#
x"
b0 !
$end
#5000
0"
1$
#10000
0$
b1 ,
#15000
b0 )
b0 +
1&
1'
1$
#16000
b10 ,
#20000
0$
#25000
1%
1#
0'
1$
#26000
b11 ,
#30000
0$
#35000
1"
0&
0#
1$
#36000
b100 ,
#40000
0$
#45000
b1 +
1#
1'
1$
#46000
b101 ,
#50000
0$
#55000
b1 !
b1 *
b10 +
1$
#56000
b110 ,
#60000
0$
#65000
b0 !
b0 *
0"
0%
0#
0'
1$
#66000
b111 ,
#70000
0$
#75000
b11 +
1'
1$
#76000
b1000 ,
#80000
0$
#85000
b100 +
1#
1$
#86000
b1001 ,
#90000
0$
#95000
1"
1%
0#
0'
1$
#96000
b1010 ,
#100000
0$
#105000
0"
0%
1$
#106000
b1011 ,
#110000
0$
#115000
1#
1$
#116000
b1100 ,
#120000
0$
#125000
b101 +
1'
1$
#126000
b1101 ,
#130000
0$
#135000
0#
0'
1$
#136000
b1110 ,
#140000
0$
#145000
1#
1$
#146000
b1111 ,
#150000
0$
#155000
1"
1%
0#
1$
#156000
b10000 ,
#160000
0$
#165000
b101 !
b101 *
1#
1$
#166000
b10001 ,
#170000
0$
#175000
b0 !
b0 *
0#
1$
#176000
b10010 ,
#180000
0$
#185000
b110 +
0"
0%
1#
1'
1$
#186000
b10011 ,
#190000
0$
#195000
1"
b111 +
1%
0#
1$
#196000
b10100 ,
#200000
0$
#205000
b111 !
b111 *
b1000 +
1#
1$
#206000
b10101 ,
#210000
0$
#215000
b0 !
b0 *
0"
0%
0'
1$
#216000
b10110 ,
#220000
0$
#225000
b1000 !
b1000 *
1"
1%
1$
#226000
b10111 ,
#230000
0$
#235000
b0 !
b0 *
0"
0%
1$
#236000
b11000 ,
#240000
0$
#245000
b1000 !
b1000 *
b1001 +
1"
1%
1'
1$
#246000
b11001 ,
#250000
0$
#255000
b1001 !
b1001 *
b1010 +
1$
#256000
b11010 ,
#260000
0$
#265000
b0 !
b0 *
b1011 +
0"
0%
1$
#266000
b11011 ,
#270000
0$
#275000
0#
0'
1$
#276000
b11100 ,
#280000
0$
#285000
b1100 +
1'
1$
#286000
b11101 ,
#290000
0$
#295000
1"
1%
0'
1$
#296000
b11110 ,
#300000
0$
#305000
b1101 +
1'
1$
#306000
b11111 ,
#310000
0$
#315000
b1101 !
b1101 *
1#
0'
1$
#316000
b100000 ,
#320000
0$
#325000
1$
#326000
b100001 ,
#330000
0$
#335000
b0 !
b0 *
b1110 +
0#
1'
1$
#336000
b100010 ,
#340000
0$
#345000
b1110 !
b1110 *
1#
0'
1$
#346000
b100011 ,
#350000
0$
#355000
1$
#356000
b100100 ,
#360000
0$
#365000
b0 !
b0 *
0"
0%
0#
1$
#366000
b100101 ,
#370000
0$
#375000
1"
b1111 +
1%
1'
1$
#376000
b100110 ,
#380000
0$
#385000
0"
0%
0'
1$
#386000
b100111 ,
#390000
0$
#395000
b1111 !
b1111 *
1"
1%
1#
1$
#396000
b101000 ,
#400000
0$
#405000
b0 !
b0 *
0#
1$
#406000
b101001 ,
#410000
0$
#415000
0"
b10000 +
0%
1'
1$
#416000
b101010 ,
#420000
0$
#425000
0'
1$
#426000
b101011 ,
#430000
0$
#435000
b10001 +
1#
1'
1$
#436000
b101100 ,
#440000
0$
#445000
b10001 !
b10001 *
b10010 +
1"
1%
1$
#446000
b101101 ,
#450000
0$
#455000
b0 !
b0 *
0"
b10011 +
0%
0#
1$
#456000
b101110 ,
#460000
0$
#465000
b10011 !
b10011 *
1"
1%
1#
0'
1$
#466000
b101111 ,
#470000
0$
#475000
b0 !
b0 *
0#
1$
#476000
b110000 ,
#480000
0$
#485000
0"
0%
1#
1$
#486000
b110001 ,
#490000
0$
#495000
b10100 +
1'
1$
#496000
b110010 ,
#500000
0$
#505000
0'
1$
#506000
b110011 ,
