Counters/rtl/xnor.v
///////////////////////////////////////////////////////////////////////////////////
///               Modeling an XNOR gate using Transmission Gates                   ///
///                                                                             ///
///////////////////////////////////////////////////////////////////////////////////
///   xnor_gate Module:                                                               ///
///                                                                             ///
///   Copyright 2025 Ujval Madhu, All rights reserved                           ///
///////////////////////////////////////////////////////////////////////////////////
//  CVS Log
//
//  Id: xnor.v, v 1.0
//
//  $Date: 2024-26-03
//  $Revision: 1.0 $
//  $Author:  Ujval Madhu

module xnor_gate(
    input in_1,
    input in_2,
    output out
);
    wire in_1_n;
    wire in_2_n;

    supply1 vdd;
    supply0 gnd;
    not n1(in_1_n, in_1);               // Not for obtaining the compliment of in_1 
    not n2(in_2_n, in_2);               // Not for obtaining the compliment of in_2 

    // Argument order: (out, in, n_ctrl, p_ctrl)
    //cmos test(out, in_1, vdd, gnd);
    cmos TG_1(out, in_1, in_2, in_2_n);      // Transmission Gate 1
    cmos TG_2(out, in_1_n, in_2_n, in_2);    // Transmission Gate 2


endmodule

Counters/rtl/xor.v
///////////////////////////////////////////////////////////////////////////////////
///               Modeling an XOR gate using Transmission Gates                   ///
///                                                                             ///
///////////////////////////////////////////////////////////////////////////////////
///   xor_gate Module:                                                               ///
///                                                                             ///
///   Copyright 2025 Ujval Madhu, All rights reserved                           ///
///////////////////////////////////////////////////////////////////////////////////
//  CVS Log
//
//  Id: xor.v, v 1.0
//
//  $Date: 2024-26-03
//  $Revision: 1.0 $
//  $Author:  Ujval Madhu

module xor_gate(
    input in_1,
    input in_2,
    output out
);
    wire in_1_n;
    wire in_2_n;

    supply1 vdd;
    supply0 gnd;
    not n1(in_1_n, in_1);               // Not for obtaining the compliment of in_1 
    not n2(in_2_n, in_2);               // Not for obtaining the compliment of in_2 

    // Argument order: (out, in, n_ctrl, p_ctrl)
    //cmos test(out, in_1, vdd, gnd);
    cmos TG_1(out, in_1, in_2_n, in_2);      // Transmission Gate 1
    cmos TG_2(out, in_1_n, in_2, in_2_n);    // Transmission Gate 2


endmodule

Modeling_Transmission_Gates/rtl/mux_2x1.v
///////////////////////////////////////////////////////////////////////////////////
///               Modeling a 2x1 Mux using Transmission Gates                   ///
///                                                                             ///
///////////////////////////////////////////////////////////////////////////////////
///   XOR Module:                                                               ///
///                                                                             ///
///   Copyright 2025 Ujval Madhu, All rights reserved                           ///
///////////////////////////////////////////////////////////////////////////////////
//  CVS Log
//
//  Id: mux_2x1.v, v 1.0
//
//  $Date: 2024-07-03
//  $Revision: 1.0 $
//  $Author:  Ujval Madhu

module mux_2x1(
    input in_1,
    input in_2,
    input sel,
    output out
);
    wire sel_n;

    not n1(sel_n,sel);               // Not for obtaining the compliment of sel 

    cmos TG_1(out, in_1, sel_n, sel);    // Transmission Gate 1
    cmos TG_2(out, in_2, sel, sel_n);    // Transmission Gate 2


endmodule

Modeling_Transmission_Gates/rtl/testbench.sv
///////////////////////////////////////////////////////////////////////////////////
///       Switch Level Modeling of a CMOS Gates and Boolean Logic               ///
///                                                                             ///
///////////////////////////////////////////////////////////////////////////////////
///   Testbench Module                                                          ///
///                                                                             ///
///   Copyright 2025 Ujval Madhu, All rights reserved                           ///
///////////////////////////////////////////////////////////////////////////////////
//  CVS Log
//
//  Id: testbench.sv, v 1.0
//
//  $Date: 2024-07-03
//  $Revision: 1.0 $
//  $Author:  Ujval Madhu

module testbench;
    reg in_a, in_b;
    reg sel;
    wire out_mux;
    wire out_xor;
    wire out_xnor;
    integer seed;

    // Instantiating 2x1 Transmission Gate MUX
    mux_2x1 m1(.in_1(in_a), .in_2(in_b), .sel(sel), .out(out_mux));

    // Instantiating Transmission Gate XOR 
    xor_gate xor1(.in_1(in_a), .in_2(in_b), .out(out_xor));

    // Instantiating Transmission Gate XNOR
    xnor_gate xnor1(.in_1(in_a), .in_2(in_b), .out(out_xnor));

    // Random Stimulus Generation
    initial begin
        seed = $random;
        $random(seed);              // Icarus doesn't support $srandom yet

        in_b = 1'b0;
        in_a = 1'b0;
        #10;
        
        for(int i = 1; i <= 20; i++) begin
            in_a = $random % 2;
            in_b = $random % 2;
            sel  = $random % 2;

            #10;
            
            $display("2x1 MUX Output: Input A: %b, Input B: %b, Sel: %b, Out: %b", in_a, in_b, sel, out_mux);
            $display("XOR Output: Input A: %b, Input B: %b, Out: %b", in_a, in_b, out_xor);
            $display("XNOR Output: Input A: %b, Input B: %b, Out: %b\n\n", in_a, in_b, out_xnor);
            //#10
            // Verification
            // // Inverter
            // if (sel == ) begin
            //     $display("Error Detected on inverter at %t, output = %b input = %b",$time, out_inv, in); 
            //     $fatal;
            // end

            // // NAND
            // if (out_nand != ~(in_a & in_b) ) begin
            //     $display("Error Detected on NAND at %t, Output = %b , Input A= %b, Input B = %b",$time, out_nand, in_a, in_b); 
            //     $fatal;
            // end
        end
    end

    // Generating Waveform Files
    initial begin
        $dumpfile("testbench.vcd");
        $dumpvars(0, testbench);
    end

endmodule

Hands_on_RTL/Atomic_Counters/waves/testbench.vcd
$date
	Wed Mar 26 14:17:52 2025
$end
$version
	Icarus Verilog
$end
$timescale
	1ps
$end
$scope module testbench $end
$var wire 1 ! out_mux $end
$var wire 1 " out_xnor $end
$var wire 1 # out_xor $end
$var reg 1 $ in_a $end
$var reg 1 % in_b $end
$var reg 1 & sel $end
$var integer 32 ' seed [31:0] $end
$scope module m1 $end
$var wire 1 $ in_1 $end
$var wire 1 % in_2 $end
$var wire 1 ! out $end
$var wire 1 & sel $end
$var wire 1 ( sel_n $end
$upscope $end
$scope module xnor1 $end
$var wire 1 ) gnd $end
$var wire 1 $ in_1 $end
$var wire 1 * in_1_n $end
$var wire 1 % in_2 $end
$var wire 1 + in_2_n $end
$var wire 1 " out $end
$var wire 1 , vdd $end
$upscope $end
$scope module xor1 $end
$var wire 1 - gnd $end
$var wire 1 $ in_1 $end
$var wire 1 . in_1_n $end
$var wire 1 % in_2 $end
$var wire 1 / in_2_n $end
$var wire 1 # out $end
$var wire 1 0 vdd $end
$upscope $end
$scope begin $ivl_for_loop0 $end
$var integer 32 1 i [31:0] $end
$upscope $end
$upscope $end
$enddefinitions $end
$comment Show the parameter values. $end
$dumpall
$end
#0
$dumpvars
b0 1
10
1/
1.
0-
1,
1+
1*
0)
x(
b11000011110100100110000111010101 '
x&
0%
0$
0#
1"
x!
$end
#10000
0(
0+
0/
1"
0*
0.
1&
1%
1!
0#
1$
b1 1
#20000
b10 1
#30000
1*
1#
1.
0"
0$
b11 1
#40000
b100 1
#50000
1(
0!
0&
b101 1
#60000
0(
1+
1/
0*
1#
0.
1&
0%
0!
0"
1$
b110 1
#70000
b111 1
#80000
1(
1"
1*
1.
0&
0#
0$
b1000 1
#90000
0(
0"
0*
0.
1&
0!
1#
1$
b1001 1
#100000
0+
0/
1!
1"
0#
1%
b1010 1
#110000
1(
1+
1/
1*
0#
1.
0&
0!
0%
1"
0$
b1011 1
#120000
0+
0/
0"
1#
1%
b1100 1
#130000
0(
0*
0#
0.
1&
1!
1"
1$
b1101 1
#140000
1(
0&
b1110 1
#150000
0(
1*
1#
1.
1&
1!
0"
0$
b1111 1
#160000
1(
1+
1/
0*
1#
0.
0&
1!
0%
0"
1$
b10000 1
#170000
1"
1*
1.
0!
0#
0$
b10001 1
#180000
0"
0*
0.
1!
1#
1$
b10010 1
#190000
0+
0/
1"
0#
1%
b10011 1
#200000
1+
1/
1*
0#
1.
0%
0!
1"
0$
b10100 1
#210000
b10101 1
