Braun_Multiplier/rtl/cla.v
///////////////////////////////////////////////////////////////////////////////////
///                      4-Bit Carry Look Ahead Adder                           ///
///                                                                             ///
///////////////////////////////////////////////////////////////////////////////////
///   CLA Module:  4-Bit Implementation of the Carry Lookahead Adder (CLA)      ///
///                                                                             ///
///   Copyright 2025 Ujval Madhu, All rights reserved                           ///
///////////////////////////////////////////////////////////////////////////////////
//  CVS Log
//
//  Id: cla.v, v 1.0
//
//  $Date: 2024-07-03
//  $Revision: 1.0 $
//  $Author:  Ujval Madhu

module cla_4b(
    input [3:0] a,
    input [3:0] b,
    input c0,      // Carry In
    output [3:0] sum,
    output c_out
);

wire [3:0] p, g;   // Propagate and Generate Bits for each bit position
wire [4:0] c;      // Carry out for each bit

assign c[0] = c0;

assign  p[0] = a[0] ^ b[0],
        p[1] = a[1] ^ b[1],
        p[2] = a[2] ^ b[2],
        p[3] = a[3] ^ b[3];

assign  g[0] = a[0] & b[0],
        g[1] = a[1] & b[1],
        g[2] = a[2] & b[2],
        g[3] = a[3] & b[3];

assign  c[1] = g[0] | (p[0] & c[0]),
        c[2] = g[1] | (p[1] & (g[0] | (p[0] & c[0]))),
        c[3] = g[2] | (p[2] & (g[1] | (p[1] & (g[0] | (p[0] & c[0]))))),
        c[4] = g[3] | (p[3] & (g[2] | (p[2] & (g[1] | (p[1] & (g[0] | (p[0] & c[0])))))));

assign  sum[0] = p[0] ^ c[0],
        sum[1] = p[1] ^ c[1],
        sum[2] = p[2] ^ c[2],
        sum[3] = p[3] ^ c[3];

assign c_out = c[4];        

endmodule

Carry_Look_Ahead_Adder/rtl/testbench.sv
///////////////////////////////////////////////////////////////////////////////////
///       Verification of Carry Look Ahead Adder                                ///
///                                                                             ///
///////////////////////////////////////////////////////////////////////////////////
///   Testbench Module: Verification using Randomized Stimulus,                 ///
///                     Functional Equivalence and Immediate Assertion          ///                                                ///
///                                                                             ///
///   Copyright 2025 Ujval Madhu, All rights reserved                           ///
///////////////////////////////////////////////////////////////////////////////////
//  CVS Log
//
//  Id: testbench.sv, v 1.0
//
//  $Date: 2024-12-03
//  $Revision: 1.0 $
//  $Author:  Ujval Madhu

module testbench;

    parameter num_bits = 4;
    parameter num_tests = 1000;

    reg [num_bits -1:0] in_a;
    reg [num_bits -1:0] in_b;
    reg c0;
    reg [num_bits -1:0]sum;
    reg [num_bits:0] expected_sum;
    reg [num_bits:0] obtained_sum;
    reg c_out;
    integer seed;

    // Instantiating the Carry Look Ahead Adder module
    cla_4b cla_adder(.a(in_a), .b(in_b), .c0(c0), .sum(sum), .c_out(c_out));
    
    ////////////////////////////////
    //    Random Stimulus Test    //
    ////////////////////////////////

    initial begin
        seed = $random;
        $random(seed);              // Icarus doesn't support $srandom yet

        in_b = 4'b0;
        in_a = 4'b0;
        c0   = 1'b0;
        #10;
        
        for(int i = 1; i <= num_tests; i++) begin
            in_a = $random % (2);
            in_b = $random % (2);
            c0   = $random % (2);

            #10;

            $display("\n Random Test %0d", i);
            $display("CLA Result: Input A: %4b, Input B: %4b, C0: %0b, Sum: %4b, C_out: %0b", in_a, in_b, c0, sum, c_out);
            $display("CLA Result: Input A: %0d, Input B: %0d, C0: %0d, Sum: %0d, C_out: %0d", in_a, in_b, c0, sum, c_out);

           //////////////////////// 
           // Functional Testing //
           ////////////////////////

            expected_sum =  in_a + in_b + c0;

            if(c_out) begin 
                obtained_sum = (1 << num_bits) + sum;
            end
            else begin
                obtained_sum = sum;
            end

            assert(expected_sum == obtained_sum)
            else begin
                $error("Sum Check Assertion error: Expected Sum = %0d, but Obtained Sum = %0d at %0t", expected_sum, obtained_sum, $time);
                $fatal;
            end
            
            #10;

        end

        $display("\nAll %0d Test cases Passed !!\n", num_tests);

    end

    // Generating Waveform Files
    initial begin
        $dumpfile("testbench.vcd");
        $dumpvars(0, testbench);
    end

endmodule

Braun_Multiplier/waves/testbench.vcd
$date
	Wed Mar 12 17:38:44 2025
$end
$version
	Icarus Verilog
$end
$timescale
	1ps
$end
$scope module testbench $end
$var wire 4 ! sum [3:0] $end
$var wire 1 " c_out $end
$var parameter 32 # num_bits $end
$var parameter 32 $ num_tests $end
$var reg 1 % c0 $end
$var reg 5 & expected_sum [4:0] $end
$var reg 4 ' in_a [3:0] $end
$var reg 4 ( in_b [3:0] $end
$var reg 5 ) obtained_sum [4:0] $end
$var integer 32 * seed [31:0] $end
$scope module cla_adder $end
$var wire 4 + a [3:0] $end
$var wire 4 , b [3:0] $end
$var wire 1 % c0 $end
$var wire 4 - sum [3:0] $end
$var wire 4 . p [3:0] $end
$var wire 4 / g [3:0] $end
$var wire 1 " c_out $end
$var wire 5 0 c [4:0] $end
$upscope $end
$scope begin $ivl_for_loop0 $end
$var integer 32 1 i [31:0] $end
$upscope $end
$upscope $end
$enddefinitions $end
$comment Show the parameter values. $end
$dumpall
b1111101000 $
b100 #
$end
#0
$dumpvars
b0 1
b0 0
b0 /
b0 .
b0 -
b0 ,
b0 +
b11000011110100100110000111010101 *
bx )
b0 (
b0 '
bx &
0%
0"
b0 !
$end
#10000
1"
b1111 !
b1111 -
b1111 /
b11111 0
1%
b1111 (
b1111 ,
b1111 '
b1111 +
b1 1
#20000
b11111 )
b11111 &
#30000
b11 !
b11 -
0"
b11 0
b1 /
b1 (
b1 ,
b1 '
b1 +
b10 1
#40000
b11 )
b11 &
#50000
b10 !
b10 -
b11 0
b1 .
b0 /
b0 '
b0 +
b11 1
#60000
b10 )
b10 &
#70000
b100 1
#90000
b1 !
b1 -
b0 0
0%
b101 1
#100000
b1 )
b1 &
#110000
1"
b0 !
b0 -
b1111 .
b11111 0
1%
b0 (
b0 ,
b1111 '
b1111 +
b110 1
#120000
b10000 )
b10000 &
#130000
b111 1
#150000
0"
b0 !
b0 -
b0 .
b0 0
0%
b0 '
b0 +
b1000 1
#160000
b0 )
b0 &
#170000
1"
b0 !
b0 -
b1111 .
b11111 0
1%
b1111 '
b1111 +
b1001 1
#180000
b10000 )
b10000 &
#190000
b1111 !
b1111 -
b0 .
b1111 /
b1111 (
b1111 ,
b1010 1
#200000
b11111 )
b11111 &
#210000
0"
b0 !
b0 -
b0 /
b0 0
0%
b0 (
b0 ,
b0 '
b0 +
b1011 1
#220000
b0 )
b0 &
#230000
b1111 !
b1111 -
b1111 .
b1111 (
b1111 ,
b1100 1
#240000
b1111 )
b1111 &
#250000
1"
b1111 !
b1111 -
b0 .
b1111 /
b11111 0
1%
b1111 '
b1111 +
b1101 1
#260000
b11111 )
b11111 &
#270000
1"
b0 !
b0 -
b1110 .
b1 /
b11110 0
0%
b1 '
b1 +
b1110 1
#280000
b10000 )
b10000 &
#290000
0"
b10 !
b10 -
b1 .
b0 /
b11 0
1%
b1 (
b1 ,
b0 '
b0 +
b1111 1
#300000
b10 )
b10 &
#310000
b1 !
b1 -
b0 0
0%
b0 (
b0 ,
b1 '
b1 +
b10000 1
#320000
b1 )
b1 &
#330000
b0 !
b0 -
b0 .
b0 '
b0 +
b10001 1
#340000
b0 )
b0 &
#350000
b1 !
b1 -
b1 .
b1 '
b1 +
b10010 1
#360000
b1 )
b1 &
#370000
1"
b11110 0
b0 !
b0 -
b1 /
b1110 .
b1 (
b1 ,
b1111 '
b1111 +
b10011 1
#380000
b10000 )
b10000 &
#390000
0"
b0 !
b0 -
b0 0
b0 .
b0 /
b0 (
b0 ,
b0 '
b0 +
b10100 1
#400000
b0 )
b0 &
#410000
1"
b0 !
b0 -
b1111 .
b11111 0
1%
b1111 (
b1111 ,
b10101 1
#420000
b10000 )
b10000 &
#430000
0"
b11 0
b11 !
b11 -
b0 .
b1 /
b1 (
b1 ,
b1 '
b1 +
b10110 1
#440000
b11 )
b11 &
#450000
b1 !
b1 -
b1 0
b0 /
b0 (
b0 ,
b0 '
b0 +
b10111 1
#460000
b1 )
b1 &
#470000
b10 !
b10 -
b1 /
b10 0
0%
b1 (
b1 ,
b1 '
b1 +
b11000 1
#480000
b10 )
b10 &
#490000
b10 !
b10 -
b1 .
b0 /
b11 0
1%
b0 '
b0 +
b11001 1
#510000
1"
b11111 0
b0 !
b0 -
b1111 .
b1111 (
b1111 ,
b11010 1
#520000
b10000 )
b10000 &
#530000
b11011 1
#550000
b0 (
b0 ,
b1111 '
b1111 +
b11100 1
#570000
0"
b1111 !
b1111 -
b0 0
0%
b11101 1
#580000
b1111 )
b1111 &
#590000
b1 !
b1 -
b0 .
b1 0
1%
b0 '
b0 +
b11110 1
#600000
b1 )
b1 &
#610000
b1 !
b1 -
b1 .
b0 0
0%
b1 '
b1 +
b11111 1
#630000
b11 !
b11 -
b0 .
b1 /
b11 0
1%
b1 (
b1 ,
b100000 1
#640000
b11 )
b11 &
#650000
1"
b0 !
b0 -
b1110 .
b11110 0
0%
b1111 '
b1111 +
b100001 1
#660000
b10000 )
b10000 &
#670000
0"
b11 !
b11 -
b0 .
b11 0
1%
b1 '
b1 +
b100010 1
#680000
b11 )
b11 &
#690000
b0 !
b0 -
b0 /
b0 0
0%
b0 (
b0 ,
b0 '
b0 +
b100011 1
#700000
b0 )
b0 &
#710000
b100100 1
#730000
b10 !
b10 -
b1 .
b11 0
1%
b1 (
b1 ,
b100101 1
#740000
b10 )
b10 &
#750000
1"
b1111 !
b1111 -
b11111 0
b0 .
b1111 /
b1111 (
b1111 ,
b1111 '
b1111 +
b100110 1
#760000
b11111 )
b11111 &
#770000
0"
b10 !
b10 -
b11 0
b1 .
b0 /
b1 (
b1 ,
b0 '
b0 +
b100111 1
#780000
b10 )
b10 &
#790000
b1 0
b1 !
b1 -
b0 .
b0 (
b0 ,
b101000 1
#800000
b1 )
b1 &
#810000
1"
b11111 0
b0 !
b0 -
b1111 .
b1111 '
b1111 +
b101001 1
#820000
b10000 )
b10000 &
#830000
b1111 !
b1111 -
b0 .
b1111 /
b1111 (
b1111 ,
b101010 1
#840000
b11111 )
b11111 &
#850000
0"
b0 !
b0 -
b0 /
b0 0
0%
b0 (
b0 ,
b0 '
b0 +
b101011 1
#860000
b0 )
b0 &
#870000
b1 !
b1 -
b1 .
b1 '
b1 +
b101100 1
#880000
b1 )
b1 &
#890000
1"
b0 !
b0 -
b1111 .
b11111 0
1%
b1111 (
b1111 ,
b0 '
b0 +
b101101 1
#900000
b10000 )
b10000 &
#910000
0"
b1 0
b1 !
b1 -
b0 .
b0 (
b0 ,
b101110 1
#920000
b1 )
b1 &
#930000
b0 !
b0 -
b0 0
0%
b101111 1
#940000
b0 )
b0 &
#950000
b1 !
b1 -
b1 .
b1 '
b1 +
b110000 1
#960000
b1 )
b1 &
#970000
b10 !
b10 -
b11 0
1%
b110001 1
#980000
b10 )
b10 &
#990000
1"
b11111 0
b1 !
b1 -
b1110 .
b1 /
b1111 (
b1111 ,
b110010 1
#1000000
b10001 )
b10001 &
#1010000
0"
b1111 !
b1111 -
b1111 .
b0 /
b0 0
0%
b0 (
b0 ,
b1111 '
b1111 +
b110011 1
#1020000
b1111 )
b1111 &
#1030000
b1 !
b1 -
b1 .
b1 (
b1 ,
b0 '
b0 +
b110100 1
#1040000
b1 )
b1 &
#1050000
b10 !
b10 -
b11 0
1%
b110101 1
#1060000
b10 )
b10 &
#1070000
b0 !
b0 -
b0 .
b0 0
0%
b0 (
b0 ,
b110110 1
#1080000
b0 )
b0 &
#1090000
b1110 !
b1110 -
1"
b11110 0
b1111 /
b1111 (
b1111 ,
b1111 '
b1111 +
b110111 1
#1100000
b11110 )
b11110 &
#1110000
0"
b1 !
b1 -
b0 /
b1 0
1%
b0 (
b0 ,
b0 '
b0 +
b111000 1
#1120000
b1 )
b1 &
#1130000
b1 !
b1 -
b1 .
b0 0
0%
b1 '
b1 +
b111001 1
#1150000
b1111 !
b1111 -
b1111 .
b1111 (
b1111 ,
b0 '
b0 +
b111010 1
#1160000
b1111 )
b1111 &
#1170000
b111011 1
#1190000
b1 !
b1 -
b0 .
b1 0
1%
b0 (
b0 ,
b111100 1
#1200000
b1 )
b1 &
#1210000
1"
b11111 0
b0 !
b0 -
b1111 .
b1111 (
b1111 ,
b111101 1
#1220000
b10000 )
b10000 &
#1230000
0"
b0 !
b0 -
b0 .
b0 0
0%
b0 (
b0 ,
b111110 1
#1240000
b0 )
b0 &
#1250000
b1 !
b1 -
b1 .
b1 (
b1 ,
b111111 1
#1260000
b1 )
b1 &
#1270000
b0 !
b0 -
b0 .
b0 (
b0 ,
b1000000 1
#1280000
b0 )
b0 &
#1290000
1"
b1111 !
b1111 -
b1111 /
b11111 0
1%
b1111 (
b1111 ,
b1111 '
b1111 +
b1000001 1
#1300000
b11111 )
b11111 &
#1310000
1"
b0 !
b0 -
b11111 0
b1111 .
b0 /
b0 '
b0 +
b1000010 1
#1320000
b10000 )
b10000 &
#1330000
0"
b1111 !
b1111 -
b0 0
0%
b0 (
b0 ,
b1111 '
b1111 +
b1000011 1
#1340000
b1111 )
b1111 &
#1350000
1"
b1 !
b1 -
b1110 .
b1 /
b11111 0
1%
b1111 (
b1111 ,
b1 '
b1 +
b1000100 1
#1360000
b10001 )
b10001 &
#1370000
b0 !
b0 -
b11110 0
0%
b1000101 1
#1380000
b10000 )
b10000 &
#1390000
b1000110 1
#1410000
0"
b0 !
b0 -
b0 0
b0 .
b0 /
b0 (
b0 ,
b0 '
b0 +
b1000111 1
#1420000
b0 )
b0 &
#1430000
1"
b0 !
b0 -
b11110 0
b1110 .
b1 /
b1111 (
b1111 ,
b1 '
b1 +
b1001000 1
#1440000
b10000 )
b10000 &
#1450000
0"
b1111 !
b1111 -
b0 0
b1111 .
b0 /
b0 '
b0 +
b1001001 1
#1460000
b1111 )
b1111 &
#1470000
b1001010 1
#1490000
b1001011 1
#1510000
b10 !
b10 -
b1 .
b11 0
1%
b1 (
b1 ,
b1001100 1
#1520000
b10 )
b10 &
#1530000
b1111 !
b1111 -
b1111 .
b0 0
0%
b0 (
b0 ,
b1111 '
b1111 +
b1001101 1
#1540000
b1111 )
b1111 &
#1550000
b1 !
b1 -
b1 .
b1 (
b1 ,
b0 '
b0 +
b1001110 1
#1560000
b1 )
b1 &
#1570000
b1001111 1
#1590000
b0 !
b0 -
b0 .
b0 (
b0 ,
b1010000 1
#1600000
b0 )
b0 &
#1610000
b1111 !
b1111 -
b1111 .
b1111 '
b1111 +
b1010001 1
#1620000
b1111 )
b1111 &
#1630000
b10 !
b10 -
b1 .
b11 0
1%
b1 (
b1 ,
b0 '
b0 +
b1010010 1
#1640000
b10 )
b10 &
#1650000
1"
b11111 0
b0 !
b0 -
b1111 .
b1111 (
b1111 ,
b1010011 1
#1660000
b10000 )
b10000 &
#1670000
b0 !
b0 -
b1110 .
b1 /
b11110 0
0%
b1 (
b1 ,
b1111 '
b1111 +
b1010100 1
#1690000
b1111 !
b1111 -
b0 .
b1111 /
b11111 0
1%
b1111 (
b1111 ,
b1010101 1
#1700000
b11111 )
b11111 &
#1710000
b1 !
b1 -
0"
b1 0
b0 /
b0 (
b0 ,
b0 '
b0 +
b1010110 1
#1720000
b1 )
b1 &
#1730000
b1010111 1
#1750000
b1 !
b1 -
b1 .
b0 0
0%
b1 '
b1 +
b1011000 1
#1770000
b1011001 1
#1790000
b10 !
b10 -
b11 0
1%
b1011010 1
#1800000
b10 )
b10 &
#1810000
1"
b11111 0
b0 !
b0 -
b1111 .
b1111 '
b1111 +
b1011011 1
#1820000
b10000 )
b10000 &
#1830000
0"
b1111 !
b1111 -
b0 0
0%
b1111 (
b1111 ,
b0 '
b0 +
b1011100 1
#1840000
b1111 )
b1111 &
#1850000
b1 !
b1 -
b1 .
b1 (
b1 ,
b1011101 1
#1860000
b1 )
b1 &
#1870000
b1 !
b1 -
b0 .
b1 0
1%
b0 (
b0 ,
b1011110 1
#1890000
b1111 !
b1111 -
1"
b11111 0
b1111 /
b1111 (
b1111 ,
b1111 '
b1111 +
b1011111 1
#1900000
b11111 )
b11111 &
#1910000
0"
b10 !
b10 -
b11 0
b1 .
b0 /
b0 (
b0 ,
b1 '
b1 +
b1100000 1
#1920000
b10 )
b10 &
#1930000
1"
b0 !
b0 -
b1110 .
b1 /
b11110 0
0%
b1111 (
b1111 ,
b1100001 1
#1940000
b10000 )
b10000 &
#1950000
0"
b0 !
b0 -
b0 0
b0 .
b0 /
b0 (
b0 ,
b0 '
b0 +
b1100010 1
#1960000
b0 )
b0 &
#1970000
b1 !
b1 -
b1 0
1%
b1100011 1
#1980000
b1 )
b1 &
#1990000
1"
b1 !
b1 -
b11111 0
b1110 .
b1 /
b1111 (
b1111 ,
b1 '
b1 +
b1100100 1
#2000000
b10001 )
b10001 &
#2010000
0"
b11 0
b11 !
b11 -
b0 .
b1 (
b1 ,
b1100101 1
#2020000
b11 )
b11 &
#2030000
1"
b0 !
b0 -
b11111 0
b1111 .
b0 /
b1111 (
b1111 ,
b0 '
b0 +
b1100110 1
#2040000
b10000 )
b10000 &
#2050000
b1111 !
b1111 -
b0 .
b1111 /
b1111 '
b1111 +
b1100111 1
#2060000
b11111 )
b11111 &
#2070000
b11 !
b11 -
0"
b11 0
b1 /
b1 (
b1 ,
b1 '
b1 +
b1101000 1
#2080000
b11 )
b11 &
#2090000
b1 !
b1 -
b1 0
b0 /
b0 (
b0 ,
b0 '
b0 +
b1101001 1
#2100000
b1 )
b1 &
#2110000
b1 !
b1 -
b1 .
b0 0
0%
b1 '
b1 +
b1101010 1
#2130000
b1 !
b1 -
b0 .
b1 0
1%
b0 '
b0 +
b1101011 1
#2150000
b0 !
b0 -
b0 0
0%
b1101100 1
#2160000
b0 )
b0 &
#2170000
b1101101 1
#2190000
b1111 !
b1111 -
b1111 .
b1111 '
b1111 +
b1101110 1
#2200000
b1111 )
b1111 &
#2210000
b1 !
b1 -
b1 .
b1 '
b1 +
b1101111 1
#2220000
b1 )
b1 &
#2230000
b1 !
b1 -
b0 .
b1 0
1%
b0 '
b0 +
b1110000 1
#2250000
1"
b1 !
b1 -
b11111 0
b1110 .
b1 /
b1 (
b1 ,
b1111 '
b1111 +
b1110001 1
#2260000
b10001 )
b10001 &
#2270000
0"
b11 0
b10 !
b10 -
b0 /
b1 .
b0 (
b0 ,
b1 '
b1 +
b1110010 1
#2280000
b10 )
b10 &
#2290000
1"
b0 !
b0 -
b1110 .
b1 /
b11110 0
0%
b1111 (
b1111 ,
b1110011 1
#2300000
b10000 )
b10000 &
#2310000
0"
b1 !
b1 -
b0 0
b1 .
b0 /
b0 (
b0 ,
b1110100 1
#2320000
b1 )
b1 &
#2330000
1"
b1110 !
b1110 -
b11110 0
b0 .
b1111 /
b1111 (
b1111 ,
b1111 '
b1111 +
b1110101 1
#2340000
b11110 )
b11110 &
#2350000
0"
b1111 !
b1111 -
b0 0
b1111 .
b0 /
b0 (
b0 ,
b1110110 1
#2360000
b1111 )
b1111 &
#2370000
b1 !
b1 -
b1 .
b1 '
b1 +
b1110111 1
#2380000
b1 )
b1 &
#2390000
b1 !
b1 -
b0 .
b1 0
1%
b0 '
b0 +
b1111000 1
#2410000
1"
b1 !
b1 -
b11111 0
b1110 .
b1 /
b1 (
b1 ,
b1111 '
b1111 +
b1111001 1
#2420000
b10001 )
b10001 &
#2430000
1"
b0 !
b0 -
b11111 0
b1111 .
b0 /
b1111 (
b1111 ,
b0 '
b0 +
b1111010 1
#2440000
b10000 )
b10000 &
#2450000
b1 !
b1 -
b1110 .
b1 /
b1 '
b1 +
b1111011 1
#2460000
b10001 )
b10001 &
#2470000
0"
b10 !
b10 -
b0 .
b10 0
0%
b1 (
b1 ,
b1111100 1
#2480000
b10 )
b10 &
#2490000
1"
b0 !
b0 -
b0 /
b1111 .
b11111 0
1%
b0 (
b0 ,
b1111 '
b1111 +
b1111101 1
#2500000
b10000 )
b10000 &
#2510000
0"
b1 0
b1 !
b1 -
b0 .
b0 '
b0 +
b1111110 1
#2520000
b1 )
b1 &
#2530000
b0 !
b0 -
b0 0
0%
b1111111 1
#2540000
b0 )
b0 &
#2550000
b1 !
b1 -
b1 0
1%
b10000000 1
#2560000
b1 )
b1 &
#2570000
b0 !
b0 -
b0 0
0%
b10000001 1
#2580000
b0 )
b0 &
#2590000
b10000010 1
#2610000
1"
b0 !
b0 -
b1111 .
b11111 0
1%
b1111 '
b1111 +
b10000011 1
#2620000
b10000 )
b10000 &
#2630000
0"
b1 0
b1 !
b1 -
b0 .
b0 '
b0 +
b10000100 1
#2640000
b1 )
b1 &
#2650000
1"
b11111 0
b0 !
b0 -
b1111 .
b1111 (
b1111 ,
b10000101 1
#2660000
b10000 )
b10000 &
#2670000
0"
b1 !
b1 -
b1 .
b0 0
0%
b1 (
b1 ,
b10000110 1
#2680000
b1 )
b1 &
#2690000
b1111 !
b1111 -
b1111 .
b0 (
b0 ,
b1111 '
b1111 +
b10000111 1
#2700000
b1111 )
b1111 &
#2710000
b1 !
b1 -
b0 .
b1 0
1%
b0 '
b0 +
b10001000 1
#2720000
b1 )
b1 &
#2730000
b1 !
b1 -
b1 .
b0 0
0%
b1 (
b1 ,
b10001001 1
#2750000
1"
b0 !
b0 -
b11110 0
b1110 .
b1 /
b1111 '
b1111 +
b10001010 1
#2760000
b10000 )
b10000 &
#2770000
0"
b10 !
b10 -
b0 /
b1 .
b11 0
1%
b0 (
b0 ,
b1 '
b1 +
b10001011 1
#2780000
b10 )
b10 &
#2790000
1"
b1110 !
b1110 -
b0 .
b1111 /
b11110 0
0%
b1111 (
b1111 ,
b1111 '
b1111 +
b10001100 1
#2800000
b11110 )
b11110 &
#2810000
b10 !
b10 -
0"
b10 0
b1 /
b1 (
b1 ,
b1 '
b1 +
b10001101 1
#2820000
b10 )
b10 &
#2830000
b10 !
b10 -
b1 .
b0 /
b11 0
1%
b0 '
b0 +
b10001110 1
#2850000
b1 0
b1 !
b1 -
b0 .
b0 (
b0 ,
b10001111 1
#2860000
b1 )
b1 &
#2870000
b1 !
b1 -
b1 .
b0 0
0%
b1 '
b1 +
b10010000 1
#2890000
b1111 !
b1111 -
b1111 .
b1111 '
b1111 +
b10010001 1
#2900000
b1111 )
b1111 &
#2910000
1"
b0 !
b0 -
b11110 0
b1110 .
b1 /
b1 (
b1 ,
b10010010 1
#2920000
b10000 )
b10000 &
#2930000
0"
b1 !
b1 -
b0 0
b1 .
b0 /
b0 '
b0 +
b10010011 1
#2940000
b1 )
b1 &
#2950000
b10 !
b10 -
b11 0
1%
b10010100 1
#2960000
b10 )
b10 &
#2970000
b1 !
b1 -
b0 0
0%
b10010101 1
#2980000
b1 )
b1 &
#2990000
1"
b1110 !
b1110 -
b11110 0
b0 .
b1111 /
b1111 (
b1111 ,
b1111 '
b1111 +
b10010110 1
#3000000
b11110 )
b11110 &
#3010000
0"
b11 !
b11 -
b1 /
b11 0
1%
b1 (
b1 ,
b1 '
b1 +
b10010111 1
#3020000
b11 )
b11 &
#3030000
1"
b0 !
b0 -
b11111 0
b1111 .
b0 /
b1111 (
b1111 ,
b0 '
b0 +
b10011000 1
#3040000
b10000 )
b10000 &
#3050000
0"
b1 !
b1 -
b1 .
b0 0
0%
b0 (
b0 ,
b1 '
b1 +
b10011001 1
#3060000
b1 )
b1 &
#3070000
b10011010 1
#3090000
b1111 !
b1111 -
b1111 .
b1111 '
b1111 +
b10011011 1
#3100000
b1111 )
b1111 &
#3110000
b10 0
b10 !
b10 -
b1 /
b0 .
b1 (
b1 ,
b1 '
b1 +
b10011100 1
#3120000
b10 )
b10 &
#3130000
b10 !
b10 -
b1 .
b0 /
b11 0
1%
b0 (
b0 ,
b10011101 1
#3150000
b11 !
b11 -
b0 .
b1 /
b1 (
b1 ,
b10011110 1
#3160000
b11 )
b11 &
#3170000
b1 !
b1 -
b1 0
b0 /
b0 (
b0 ,
b0 '
b0 +
b10011111 1
#3180000
b1 )
b1 &
#3190000
b1111 !
b1111 -
b1111 .
b0 0
0%
b1111 (
b1111 ,
b10100000 1
#3200000
b1111 )
b1111 &
#3210000
1"
b0 !
b0 -
b11110 0
b1110 .
b1 /
b1 '
b1 +
b10100001 1
#3220000
b10000 )
b10000 &
#3230000
1"
b0 !
b0 -
b1111 .
b0 /
b11111 0
1%
b0 '
b0 +
b10100010 1
#3250000
0"
b1111 !
b1111 -
b0 0
0%
b0 (
b0 ,
b1111 '
b1111 +
b10100011 1
#3260000
b1111 )
b1111 &
#3270000
b10100100 1
#3290000
1"
b1 !
b1 -
b1110 .
b1 /
b11111 0
1%
b1111 (
b1111 ,
b1 '
b1 +
b10100101 1
#3300000
b10001 )
b10001 &
#3310000
0"
b10 !
b10 -
b11 0
b1 .
b0 /
b1 (
b1 ,
b0 '
b0 +
b10100110 1
#3320000
b10 )
b10 &
#3330000
b0 !
b0 -
b0 .
b0 0
0%
b0 (
b0 ,
b10100111 1
#3340000
b0 )
b0 &
#3350000
1"
b1 !
b1 -
b1110 .
b1 /
b11111 0
1%
b1111 (
b1111 ,
b1 '
b1 +
b10101000 1
#3360000
b10001 )
b10001 &
#3370000
0"
b0 !
b0 -
b0 .
b0 /
b0 0
0%
b0 (
b0 ,
b0 '
b0 +
b10101001 1
#3380000
b0 )
b0 &
#3390000
1"
b1 !
b1 -
b1110 .
b1 /
b11111 0
1%
b1 (
b1 ,
b1111 '
b1111 +
b10101010 1
#3400000
b10001 )
b10001 &
#3410000
1"
b0 !
b0 -
b11111 0
b1111 .
b0 /
b0 (
b0 ,
b10101011 1
#3420000
b10000 )
b10000 &
#3430000
0"
b11 0
b11 !
b11 -
b1 /
b0 .
b1 (
b1 ,
b1 '
b1 +
b10101100 1
#3440000
b11 )
b11 &
#3450000
1"
b11111 0
b1 !
b1 -
b1110 .
b1111 (
b1111 ,
b10101101 1
#3460000
b10001 )
b10001 &
#3470000
0"
b1111 !
b1111 -
b1111 .
b0 /
b0 0
0%
b0 '
b0 +
b10101110 1
#3480000
b1111 )
b1111 &
#3490000
b1 !
b1 -
b0 .
b1 0
1%
b0 (
b0 ,
b10101111 1
#3500000
b1 )
b1 &
#3510000
b11 !
b11 -
b11 0
b1 /
b1 (
b1 ,
b1 '
b1 +
b10110000 1
#3520000
b11 )
b11 &
#3530000
b1111 !
b1111 -
1"
b11111 0
b1111 /
b1111 (
b1111 ,
b1111 '
b1111 +
b10110001 1
#3540000
b11111 )
b11111 &
#3550000
b1110 !
b1110 -
b11110 0
0%
b10110010 1
#3560000
b11110 )
b11110 &
#3570000
0"
b1 !
b1 -
b0 /
b1 0
1%
b0 (
b0 ,
b0 '
b0 +
b10110011 1
#3580000
b1 )
b1 &
#3590000
b0 !
b0 -
b0 0
0%
b10110100 1
#3600000
b0 )
b0 &
#3610000
b1110 !
b1110 -
1"
b11110 0
b1111 /
b1111 (
b1111 ,
b1111 '
b1111 +
b10110101 1
#3620000
b11110 )
b11110 &
#3630000
0"
b1 !
b1 -
b0 /
b1 0
1%
b0 (
b0 ,
b0 '
b0 +
b10110110 1
#3640000
b1 )
b1 &
#3650000
b11 0
b10 !
b10 -
b1 .
b1 '
b1 +
b10110111 1
#3660000
b10 )
b10 &
#3670000
b1111 !
b1111 -
b1111 .
b0 0
0%
b1111 (
b1111 ,
b0 '
b0 +
b10111000 1
#3680000
b1111 )
b1111 &
#3690000
b1 !
b1 -
b0 .
b1 0
1%
b0 (
b0 ,
b10111001 1
#3700000
b1 )
b1 &
#3710000
1"
b0 !
b0 -
b1110 .
b1 /
b11110 0
0%
b1111 (
b1111 ,
b1 '
b1 +
b10111010 1
#3720000
b10000 )
b10000 &
#3730000
1"
b0 !
b0 -
b1111 .
b0 /
b11111 0
1%
b0 (
b0 ,
b1111 '
b1111 +
b10111011 1
#3750000
b1111 (
b1111 ,
b0 '
b0 +
b10111100 1
#3770000
0"
b0 !
b0 -
b0 .
b0 0
0%
b0 (
b0 ,
b10111101 1
#3780000
b0 )
b0 &
#3790000
b10 !
b10 -
b1 .
b11 0
1%
b1 (
b1 ,
b10111110 1
#3800000
b10 )
b10 &
#3810000
b1 0
b1 !
b1 -
b0 .
b0 (
b0 ,
b10111111 1
#3820000
b1 )
b1 &
#3830000
b1 !
b1 -
b1 .
b0 0
0%
b1 (
b1 ,
b11000000 1
#3850000
1"
b0 !
b0 -
b11110 0
b1110 .
b1 /
b1111 (
b1111 ,
b1 '
b1 +
b11000001 1
#3860000
b10000 )
b10000 &
#3870000
b11000010 1
#3890000
0"
b0 !
b0 -
b0 0
b0 .
b0 /
b0 (
b0 ,
b0 '
b0 +
b11000011 1
#3900000
b0 )
b0 &
#3910000
1"
b1 !
b1 -
b1110 .
b1 /
b11111 0
1%
b1 (
b1 ,
b1111 '
b1111 +
b11000100 1
#3920000
b10001 )
b10001 &
#3930000
b0 !
b0 -
b11110 0
0%
b1111 (
b1111 ,
b1 '
b1 +
b11000101 1
#3940000
b10000 )
b10000 &
#3950000
0"
b0 !
b0 -
b0 0
b0 .
b0 /
b0 (
b0 ,
b0 '
b0 +
b11000110 1
#3960000
b0 )
b0 &
#3970000
b11000111 1
#3990000
1"
b1111 !
b1111 -
b1111 /
b11111 0
1%
b1111 (
b1111 ,
b1111 '
b1111 +
b11001000 1
#4000000
b11111 )
b11111 &
#4010000
b11 !
b11 -
0"
b11 0
b1 /
b1 (
b1 ,
b1 '
b1 +
b11001001 1
#4020000
b11 )
b11 &
#4030000
0"
b1111 !
b1111 -
b0 /
b1111 .
b0 0
0%
b0 (
b0 ,
b1111 '
b1111 +
b11001010 1
#4040000
b1111 )
b1111 &
#4050000
b0 !
b0 -
b0 .
b0 '
b0 +
b11001011 1
#4060000
b0 )
b0 &
#4070000
b10 !
b10 -
b1 .
b11 0
1%
b1 (
b1 ,
b11001100 1
#4080000
b10 )
b10 &
#4090000
b1 !
b1 -
b0 0
0%
b11001101 1
#4100000
b1 )
b1 &
#4110000
1"
b1 !
b1 -
b1110 .
b1 /
b11111 0
1%
b1111 '
b1111 +
b11001110 1
